{"nome":"Hideo Nakata","genero":2,"popularidade":6.038}
{"nome":"Jean-Baptiste Andrea","genero":2,"popularidade":1.542}
{"nome":"Fabrice Canepa","genero":0,"popularidade":1.96}
{"nome":"Kurt Wimmer","genero":2,"popularidade":9.963}
{"nome":"Stevan Mena","genero":2,"popularidade":2.523}
{"nome":"Wilhelm Liebenberg","genero":2,"popularidade":1.96}
{"nome":"James Cameron","genero":2,"popularidade":11.568}
{"nome":"Sebastian Gutierrez","genero":2,"popularidade":2.887}
{"nome":"William Brent Bell","genero":2,"popularidade":3.627}
{"nome":"Hans-Christian Schmid","genero":2,"popularidade":2.062}
{"nome":"Ringan Ledwidge","genero":0,"popularidade":1.166}
{"nome":"Zev Berman","genero":0,"popularidade":1.62}
{"nome":"David Moreau","genero":2,"popularidade":3.868}
{"nome":"Xavier Palud","genero":2,"popularidade":2.04}
{"nome":"Steve Miner","genero":2,"popularidade":3.978}
{"nome":"J.T. Petty","genero":2,"popularidade":3.185}
{"nome":"Robby Henson","genero":2,"popularidade":1.696}
{"nome":"\u00c1lex de la Iglesia","genero":2,"popularidade":1.817}
{"nome":"Gregory Hoblit","genero":2,"popularidade":5.188}
{"nome":"Jaume Balaguer\u00f3","genero":2,"popularidade":4.028}
{"nome":"Paco Plaza","genero":2,"popularidade":8.397}
{"nome":"Richard Kelly","genero":2,"popularidade":2.32}
{"nome":"David Nerlich","genero":2,"popularidade":0.98}
{"nome":"Andrew Traucki","genero":2,"popularidade":5.128}
{"nome":"Masayuki Ochiai","genero":2,"popularidade":4.666}
{"nome":"Scott Stewart","genero":0,"popularidade":0.691}
{"nome":"Jed Weintrob","genero":0,"popularidade":1.788}
{"nome":"David S. Goyer","genero":2,"popularidade":11.297}
{"nome":"Toby Wilkins","genero":2,"popularidade":1.317}
{"nome":"Jaume Collet-Serra","genero":2,"popularidade":6.14}
{"nome":"Paul Solet","genero":2,"popularidade":6.062}
{"nome":"Daniel Myrick","genero":2,"popularidade":4.732}
{"nome":"Joel Anderson","genero":2,"popularidade":3.112}
{"nome":"William Nigh","genero":2,"popularidade":2.271}
{"nome":"Park Chan-wook","genero":2,"popularidade":8.76}
{"nome":"Fred Walton","genero":2,"popularidade":2.474}
{"nome":"Chris Nahon","genero":2,"popularidade":5.259}
{"nome":"Rob Stefaniuk","genero":2,"popularidade":4.742}
{"nome":"Joey Stewart","genero":2,"popularidade":1.594}
{"nome":"Adam Green","genero":2,"popularidade":4.185}
{"nome":"Daniel Grou","genero":2,"popularidade":1.732}
{"nome":"Nimr\u00f3d Antal","genero":2,"popularidade":8.501}
{"nome":"Peter Robinson","genero":2,"popularidade":1.594}
{"nome":"Mike Newell","genero":2,"popularidade":9.752}
{"nome":"Mervyn LeRoy","genero":2,"popularidade":5.12}
{"nome":"Alfred Hitchcock","genero":2,"popularidade":13.767}
{"nome":"Bob Clark","genero":2,"popularidade":5.262}
{"nome":"John Frankenheimer","genero":2,"popularidade":5.002}
{"nome":"Herschell Gordon Lewis","genero":2,"popularidade":3.693}
{"nome":"Edgar G. Ulmer","genero":2,"popularidade":1.385}
{"nome":"Herk Harvey","genero":2,"popularidade":3.046}
{"nome":"Robert Kaylor","genero":0,"popularidade":1.62}
{"nome":"Paul Leni","genero":2,"popularidade":2.148}
{"nome":"Jacques Tourneur","genero":2,"popularidade":4.822}
{"nome":"Paul Schrader","genero":2,"popularidade":4.814}
{"nome":"Fritz Kiersch","genero":2,"popularidade":2.968}
{"nome":"Jack Arnold","genero":2,"popularidade":7.258}
{"nome":"Rospo Pallenberg","genero":2,"popularidade":2.653}
{"nome":"George A. Romero","genero":2,"popularidade":5.741}
{"nome":"Mark Goldblatt","genero":2,"popularidade":3.503}
{"nome":"Lamberto Bava","genero":2,"popularidade":3.933}
{"nome":"Tod Browning","genero":2,"popularidade":5.216}
{"nome":"Stuart Gordon","genero":2,"popularidade":8.964}
{"nome":"Rouben Mamoulian","genero":2,"popularidade":4.26}
{"nome":"Dan Curtis","genero":2,"popularidade":5.265}
{"nome":"Tobe Hooper","genero":2,"popularidade":4.255}
{"nome":"Peter Yates","genero":2,"popularidade":2.85}
{"nome":"Kurt Neumann","genero":2,"popularidade":2.051}
{"nome":"David Cronenberg","genero":2,"popularidade":12.039}
{"nome":"Tom Holland","genero":2,"popularidade":47.272}
{"nome":"Bruce D. Clark","genero":2,"popularidade":0.949}
{"nome":"William Girdler","genero":2,"popularidade":1.535}
{"nome":"John Carpenter","genero":2,"popularidade":13.512}
{"nome":"Oliver Stone","genero":2,"popularidade":10.316}
{"nome":"Robert Wise","genero":2,"popularidade":4.627}
{"nome":"Wes Craven","genero":2,"popularidade":6.705}
{"nome":"Colin Cairnes","genero":0,"popularidade":1.96}
{"nome":"Cameron Cairnes","genero":0,"popularidade":1.382}
{"nome":"Sidney Lanfield","genero":2,"popularidade":3.683}
{"nome":"William Castle","genero":2,"popularidade":3.353}
{"nome":"Wallace Worsley","genero":2,"popularidade":1.96}
{"nome":"John Hough","genero":2,"popularidade":1.915}
{"nome":"Philip Kaufman","genero":2,"popularidade":5.093}
{"nome":"James Whale","genero":2,"popularidade":1.508}
{"nome":"Michael Ritchie","genero":2,"popularidade":4.569}
{"nome":"Don Taylor","genero":2,"popularidade":7.794}
{"nome":"Larry Cohen","genero":2,"popularidade":2.704}
{"nome":"Ernest B. Schoedsack","genero":2,"popularidade":2.44}
{"nome":"Merian C. Cooper","genero":2,"popularidade":6.9}
{"nome":"John Guillermin","genero":2,"popularidade":4.832}
{"nome":"Roger Corman","genero":2,"popularidade":9.516}
{"nome":"Frank Oz","genero":2,"popularidade":10.57}
{"nome":"Bob Swaim","genero":2,"popularidade":3.355}
{"nome":"Terence Fisher","genero":2,"popularidade":2.129}
{"nome":"Kathryn Bigelow","genero":1,"popularidade":6.338}
{"nome":"Richard Donner","genero":2,"popularidade":7.548}
{"nome":"Michael Schroeder","genero":2,"popularidade":1.754}
{"nome":"Rupert Julian","genero":2,"popularidade":1.401}
{"nome":"Edward Sedgwick","genero":2,"popularidade":4.348}
{"nome":"Albert Lewin","genero":2,"popularidade":3.565}
{"nome":"Joe Dante","genero":2,"popularidade":4.081}
{"nome":"Paul Lynch","genero":0,"popularidade":0.608}
{"nome":"Joseph Zito","genero":2,"popularidade":5.128}
{"nome":"Paul Golding","genero":0,"popularidade":1.532}
{"nome":"Richard Fleischer","genero":2,"popularidade":3.189}
{"nome":"Archie Mayo","genero":2,"popularidade":2.77}
{"nome":"Gordon Douglas","genero":2,"popularidade":4.6}
{"nome":"Christian Nyby","genero":2,"popularidade":3.948}
{"nome":"Sergio Martino","genero":2,"popularidade":3.716}
{"nome":"Piers Haggard","genero":2,"popularidade":4.871}
{"nome":"Wolf Rilla","genero":2,"popularidade":2.651}
{"nome":"Daniel Mann","genero":2,"popularidade":1.761}
{"nome":"William Friedkin","genero":2,"popularidade":8.857}
{"nome":"Anatole Litvak","genero":2,"popularidade":6.958}
{"nome":"Todd Haynes","genero":2,"popularidade":2.815}
{"nome":"Lewis Allen","genero":2,"popularidade":6.119}
{"nome":"Eric Red","genero":2,"popularidade":1.603}
{"nome":"David Wickes","genero":2,"popularidade":2.305}
{"nome":"Edward Ludwig","genero":2,"popularidade":1.128}
{"nome":"Dario Argento","genero":2,"popularidade":9.252}
{"nome":"Ubaldo Ragona","genero":2,"popularidade":0.6}
{"nome":"Sidney Salkow","genero":2,"popularidade":1.381}
{"nome":"Mike Nichols","genero":2,"popularidade":1.781}
{"nome":"Robert Wiene","genero":2,"popularidade":4.666}
{"nome":"Jonathan Demme","genero":2,"popularidade":6.69}
{"nome":"Brett Leonard","genero":2,"popularidade":3.416}
{"nome":"Bill Mizel","genero":0,"popularidade":0.84}
{"nome":"Gregory Widen","genero":2,"popularidade":8.173}
{"nome":"Jon Amiel","genero":2,"popularidade":1.567}
{"nome":"Abel Ferrara","genero":2,"popularidade":12.225}
{"nome":"James Foley","genero":2,"popularidade":3.525}
{"nome":"Brian Yuzna","genero":2,"popularidade":7.215}
{"nome":"Michael Cooney","genero":2,"popularidade":1.98}
{"nome":"Ole Bornedal","genero":2,"popularidade":6.464}
{"nome":"Stephen Norrington","genero":2,"popularidade":3.507}
{"nome":"Thomas Lee","genero":0,"popularidade":0.6}
{"nome":"Francis Ford Coppola","genero":2,"popularidade":10.599}
{"nome":"Walter Hill","genero":2,"popularidade":5.367}
{"nome":"Gus Van Sant","genero":2,"popularidade":4.687}
{"nome":"John Bruno","genero":2,"popularidade":8.498}
{"nome":"Stephen Sommers","genero":2,"popularidade":13.2}
{"nome":"Renny Harlin","genero":2,"popularidade":7.108}
{"nome":"Jan de Bont","genero":2,"popularidade":7.287}
{"nome":"William Malone","genero":2,"popularidade":4.639}
{"nome":"Mike Nicholson","genero":0,"popularidade":0.6}
{"nome":"Jon Bokenkamp","genero":2,"popularidade":3.954}
{"nome":"Alejandro Amen\u00e1bar","genero":2,"popularidade":8.872}
{"nome":"Sheldon Lettich","genero":2,"popularidade":5.821}
{"nome":"Robert Harmon","genero":2,"popularidade":8.067}
{"nome":"Dick Maas","genero":2,"popularidade":4.049}
{"nome":"David Carson","genero":2,"popularidade":7.09}
{"nome":"Eli Roth","genero":2,"popularidade":16.319}
{"nome":"Uwe Boll","genero":2,"popularidade":4.735}
{"nome":"Tony Piccirillo","genero":2,"popularidade":0.6}
{"nome":"Alex Turner","genero":2,"popularidade":3.086}
{"nome":"David Winkler","genero":2,"popularidade":3.711}
{"nome":"Iain Softley","genero":2,"popularidade":1.4}
{"nome":"Paul Etheredge","genero":2,"popularidade":5.615}
{"nome":"Jim Gillespie","genero":2,"popularidade":4.109}
{"nome":"Ian Gamazon","genero":0,"popularidade":0.6}
{"nome":"Neill Dela Llana","genero":0,"popularidade":0.6}
{"nome":"Nicholas Mastandrea","genero":2,"popularidade":3.693}
{"nome":"Ryan Schifrin","genero":0,"popularidade":1.263}
{"nome":"Lucky McKee","genero":2,"popularidade":3.063}
{"nome":"Christian Alvart","genero":2,"popularidade":4.503}
{"nome":"Jake West","genero":2,"popularidade":2.552}
{"nome":"Tony Maylam","genero":2,"popularidade":2.198}
{"nome":"Peter Cornwell","genero":2,"popularidade":5.32}
{"nome":"Peter Jackson","genero":2,"popularidade":18.009}
{"nome":"Joel Schumacher","genero":2,"popularidade":3.852}
{"nome":"Paul Andrew Williams","genero":2,"popularidade":1.754}
{"nome":"Kit Ryan","genero":2,"popularidade":1.712}
{"nome":"Joe Johnston","genero":2,"popularidade":6.773}
{"nome":"John Erick Dowdle","genero":2,"popularidade":1.785}
{"nome":"Bruce Campbell","genero":2,"popularidade":15.442}
{"nome":"Alexandre Aja","genero":2,"popularidade":5.536}
{"nome":"Ken Russell","genero":2,"popularidade":5.428}
{"nome":"Sean S. Cunningham","genero":2,"popularidade":2.759}
{"nome":"Monte Hellman","genero":2,"popularidade":3.838}
{"nome":"John Gaeta","genero":2,"popularidade":5.749}
{"nome":"Darren Lynn Bousman","genero":2,"popularidade":6.466}
{"nome":"Oliver Parker","genero":2,"popularidade":7.055}
{"nome":"Ana Kokkinos","genero":1,"popularidade":1.484}
{"nome":"Gregg Bishop","genero":2,"popularidade":1.4}
{"nome":"Dennis Iliadis","genero":2,"popularidade":6.014}
{"nome":"Breck Eisner","genero":2,"popularidade":2.53}
{"nome":"David Ondaatje","genero":0,"popularidade":1.45}
{"nome":"Vincenzo Natali","genero":2,"popularidade":8.026}
{"nome":"Fabrice Du Welz","genero":2,"popularidade":2.108}
{"nome":"Lars von Trier","genero":2,"popularidade":15.138}
{"nome":"Tennyson Bardwell","genero":0,"popularidade":1.4}
{"nome":"Conor McPherson","genero":2,"popularidade":1.388}
{"nome":"Morgan J. Freeman","genero":2,"popularidade":2.371}
{"nome":"Marcus Dunstan","genero":2,"popularidade":9.719}
{"nome":"Dave Parker","genero":2,"popularidade":2.831}
{"nome":"Johnny Kevorkian","genero":2,"popularidade":0.729}
{"nome":"Gadi Harel","genero":0,"popularidade":2.71}
{"nome":"Marcel Sarmiento","genero":2,"popularidade":2.174}
{"nome":"David Pastor","genero":2,"popularidade":5.505}
{"nome":"Alex Pastor","genero":0,"popularidade":0.6}
{"nome":"Glenn McQuaid","genero":2,"popularidade":2.313}
{"nome":"Donald P. Borchers","genero":2,"popularidade":3.02}
{"nome":"Gerard Johnson","genero":2,"popularidade":1.798}
{"nome":"Victor Zarcoff","genero":0,"popularidade":1.96}
{"nome":"Daniel Stamm","genero":2,"popularidade":2.939}
{"nome":"Mikael H\u00e5fstr\u00f6m","genero":2,"popularidade":6.69}
{"nome":"Seth Fuller","genero":0,"popularidade":1.38}
{"nome":"Scott Hussion","genero":0,"popularidade":1.22}
{"nome":"David Marmor","genero":0,"popularidade":0.6}
{"nome":"Petra Korner","genero":1,"popularidade":0.972}
{"nome":"Danny Boyle","genero":2,"popularidade":17.157}
{"nome":"Juan Carlos Fresnadillo","genero":2,"popularidade":2.789}
{"nome":"Ben Ketai","genero":2,"popularidade":3.568}
{"nome":"David Slade","genero":2,"popularidade":4.267}
{"nome":"Rob Zombie","genero":2,"popularidade":7.51}
{"nome":"Dylan Reynolds","genero":0,"popularidade":1.176}
{"nome":"Bj\u00f6rn Stein","genero":2,"popularidade":6.788}
{"nome":"M\u00e5ns M\u00e5rlind","genero":2,"popularidade":7.98}
{"nome":"Robert Englund","genero":2,"popularidade":12.844}
{"nome":"Liam Gavin","genero":2,"popularidade":2.573}
{"nome":"Ben Wheatley","genero":2,"popularidade":8.169}
{"nome":"Ana Lily Amirpour","genero":1,"popularidade":5.513}
{"nome":"Adam Wingard","genero":2,"popularidade":9.3}
{"nome":"Jack Sholder","genero":2,"popularidade":7.757}
{"nome":"Chuck Russell","genero":2,"popularidade":8.204}
{"nome":"Stephen Hopkins","genero":2,"popularidade":5.148}
{"nome":"John Krasinski","genero":2,"popularidade":21.997}
{"nome":"Kim Jee-woon","genero":2,"popularidade":6.769}
{"nome":"Stephen Gaghan","genero":2,"popularidade":5.276}
{"nome":"Charles Barton","genero":2,"popularidade":1.735}
{"nome":"Charles Lamont","genero":2,"popularidade":1.485}
{"nome":"Navot Papushado","genero":2,"popularidade":1.742}
{"nome":"Bill Plympton","genero":2,"popularidade":8.331}
{"nome":"Chris Nash","genero":2,"popularidade":3.518}
{"nome":"Dennison Ramalho","genero":2,"popularidade":1.96}
{"nome":"Erik Matti","genero":2,"popularidade":6.833}
{"nome":"E.L. Katz","genero":2,"popularidade":1.766}
{"nome":"Hajime Ohata","genero":2,"popularidade":3.287}
{"nome":"Jen Soska","genero":1,"popularidade":4.145}
{"nome":"Sylvia Soska","genero":1,"popularidade":6.419}
{"nome":"Jerome Sable","genero":2,"popularidade":1.859}
{"nome":"Jim Hosking","genero":2,"popularidade":4.445}
{"nome":"Juan Mart\u00ednez Moreno","genero":2,"popularidade":0.618}
{"nome":"Julian Barratt","genero":2,"popularidade":7.862}
{"nome":"Julian Gilbey","genero":2,"popularidade":3.685}
{"nome":"Alexandre Bustillo","genero":2,"popularidade":3.195}
{"nome":"Julien Maury","genero":2,"popularidade":4.187}
{"nome":"Kristina Buozyte","genero":1,"popularidade":2.07}
{"nome":"Bruno Samper","genero":2,"popularidade":1.4}
{"nome":"Alejandro Brugu\u00e9s","genero":2,"popularidade":5.202}
{"nome":"Larry Fessenden","genero":2,"popularidade":7.805}
{"nome":"Marvin Kren","genero":2,"popularidade":4.137}
{"nome":"Robert Morgan","genero":2,"popularidade":4.41}
{"nome":"Rodney Ascher","genero":2,"popularidade":6.09}
{"nome":"S\u00f4ichi Umezawa","genero":2,"popularidade":1.96}
{"nome":"Steven Kostanski","genero":2,"popularidade":9.475}
{"nome":"Todd Rohal","genero":2,"popularidade":3.478}
{"nome":"Lancelot Oduwa Imasuen","genero":2,"popularidade":1.4}
{"nome":"Timur Bekmambetov","genero":2,"popularidade":3.445}
{"nome":"Jimmy Loweree","genero":0,"popularidade":1.905}
{"nome":"Mike Flanagan","genero":2,"popularidade":4.52}
{"nome":"Jon Hewitt","genero":0,"popularidade":3.996}
{"nome":"Barry Sonnenfeld","genero":2,"popularidade":7.293}
{"nome":"Agnieszka Wojtowicz-Vosloo","genero":1,"popularidade":0.98}
{"nome":"Jeremy Gardner","genero":2,"popularidade":9.229}
{"nome":"Christian Stella","genero":0,"popularidade":1.771}
{"nome":"Peter Engert","genero":0,"popularidade":1.614}
{"nome":"Alfred Sole","genero":2,"popularidade":3.709}
{"nome":"David Fincher","genero":2,"popularidade":28.459}
{"nome":"Matty Beckerman","genero":0,"popularidade":0.693}
{"nome":"Ben Rock","genero":2,"popularidade":2.817}
{"nome":"Jean-Pierre Jeunet","genero":2,"popularidade":5.974}
{"nome":"Chris Sivertson","genero":2,"popularidade":4.388}
{"nome":"Joe Begos","genero":2,"popularidade":2.775}
{"nome":"Jason DeVan","genero":0,"popularidade":1.995}
{"nome":"Rob Schmidt","genero":2,"popularidade":9.6}
{"nome":"Courtney Solomon","genero":2,"popularidade":3.637}
{"nome":"Mary Harron","genero":1,"popularidade":4.005}
{"nome":"Morgan Freeman","genero":2,"popularidade":69.016}
{"nome":"John Landis","genero":2,"popularidade":8.039}
{"nome":"Grace Lee","genero":0,"popularidade":0.6}
{"nome":"Tony Randel","genero":2,"popularidade":6.672}
{"nome":"Damiano Damiani","genero":2,"popularidade":6.527}
{"nome":"Franck Khalfoun","genero":2,"popularidade":8.446}
{"nome":"Michael Polish","genero":2,"popularidade":2.008}
{"nome":"Romola Garai","genero":1,"popularidade":20.307}
{"nome":"Luis Llosa","genero":2,"popularidade":4.035}
{"nome":"Stefan Ruzowitzky","genero":2,"popularidade":2.873}
{"nome":"Marcos Efron","genero":2,"popularidade":0.694}
{"nome":"Antonio Margheriti","genero":2,"popularidade":4.193}
{"nome":"Paul Morrissey","genero":2,"popularidade":9.873}
{"nome":"Ib Melchior","genero":2,"popularidade":2.054}
{"nome":"Sonny Mallhi","genero":2,"popularidade":4.93}
{"nome":"Brett Simmons","genero":2,"popularidade":2.861}
{"nome":"John McPhail","genero":2,"popularidade":1.212}
{"nome":"John R. Leonetti","genero":2,"popularidade":3.569}
{"nome":"Gary Dauberman","genero":2,"popularidade":10.305}
{"nome":"David F. Sandberg","genero":2,"popularidade":4.022}
{"nome":"Jason Bognacki","genero":0,"popularidade":1.4}
{"nome":"Lowell Dean","genero":0,"popularidade":1.62}
{"nome":"Gerard Bush","genero":2,"popularidade":1.4}
{"nome":"Danny Perez","genero":0,"popularidade":1.4}
{"nome":"Cody Calahan","genero":2,"popularidade":1.96}
{"nome":"Brandon Cronenberg","genero":2,"popularidade":3.762}
{"nome":"David Amito","genero":0,"popularidade":2.132}
{"nome":"Michael Laicini","genero":0,"popularidade":0.98}
{"nome":"Gonzalo L\u00f3pez-Gallego","genero":2,"popularidade":2.044}
{"nome":"Bryan Singer","genero":2,"popularidade":9.741}
{"nome":"Renaud Gauthier","genero":2,"popularidade":2.188}
{"nome":"Frank Marshall","genero":2,"popularidade":5.841}
{"nome":"Jonathan Watson","genero":0,"popularidade":1.103}
{"nome":"John Stockwell","genero":2,"popularidade":12.87}
{"nome":"Sam Raimi","genero":2,"popularidade":11.9}
{"nome":"Tom Botchii Skowronski","genero":0,"popularidade":0.98}
{"nome":"Peter Newbrook","genero":2,"popularidade":3.656}
{"nome":"Rand Ravich","genero":2,"popularidade":1.186}
{"nome":"Nicholas McCarthy","genero":2,"popularidade":1.774}
{"nome":"David Allen Brooks","genero":2,"popularidade":3.958}
{"nome":"David Brooks","genero":0,"popularidade":1.141}
{"nome":"John De Bello","genero":2,"popularidade":1.698}
{"nome":"Dominik Hartl","genero":0,"popularidade":1.4}
{"nome":"Shinji Higuchi","genero":2,"popularidade":4.611}
{"nome":"Takashi Miike","genero":2,"popularidade":11.539}
{"nome":"Jordan Galland","genero":2,"popularidade":3.227}
{"nome":"Michael S. Ojeda","genero":2,"popularidade":0.694}
{"nome":"Colin Strause","genero":2,"popularidade":5.002}
{"nome":"Greg Strause","genero":2,"popularidade":6.306}
{"nome":"Adam MacDonald","genero":2,"popularidade":2.325}
{"nome":"Tim Reis","genero":0,"popularidade":0.98}
{"nome":"Jacob Vaughan","genero":2,"popularidade":2.744}
{"nome":"Kimble Rendall","genero":2,"popularidade":1.42}
{"nome":"Paul Verhoeven","genero":2,"popularidade":7.541}
{"nome":"Frank Henenlotter","genero":2,"popularidade":5.228}
{"nome":"Can Evrenol","genero":2,"popularidade":3.654}
{"nome":"Roland West","genero":2,"popularidade":4.563}
{"nome":"Louis Morneau","genero":2,"popularidade":2.085}
{"nome":"Roger Christian","genero":2,"popularidade":1.999}
{"nome":"Eug\u00e8ne Louri\u00e9","genero":2,"popularidade":3.344}
{"nome":"Philippe Mora","genero":2,"popularidade":4.753}
{"nome":"Mark Robson","genero":2,"popularidade":2.449}
{"nome":"Tim Burton","genero":2,"popularidade":13.276}
{"nome":"Scott Glosserman","genero":2,"popularidade":3.074}
{"nome":"Matthew Whedon","genero":2,"popularidade":0.98}
{"nome":"Andrew Mecham","genero":2,"popularidade":1.537}
{"nome":"William Beaudine","genero":2,"popularidade":11.744}
{"nome":"Emilio Portes","genero":2,"popularidade":2.299}
{"nome":"Phil Karlson","genero":2,"popularidade":2.196}
{"nome":"Michael Haneke","genero":2,"popularidade":6.933}
{"nome":"Peter Strickland","genero":2,"popularidade":3.576}
{"nome":"James Cullen Bressack","genero":2,"popularidade":4.125}
{"nome":"Chris Peckover","genero":2,"popularidade":1.28}
{"nome":"Lucio Fulci","genero":2,"popularidade":9.064}
{"nome":"Panos Cosmatos","genero":2,"popularidade":8.907}
{"nome":"Jackson Stewart","genero":2,"popularidade":2.744}
{"nome":"Ram Gopal Varma","genero":2,"popularidade":4.292}
{"nome":"Corey Grant","genero":2,"popularidade":1.4}
{"nome":"Jefferson Moneo","genero":0,"popularidade":1.176}
{"nome":"James Nguyen","genero":2,"popularidade":5.172}
{"nome":"Brad Michael Elmore","genero":0,"popularidade":0.98}
{"nome":"Chad Archibald","genero":2,"popularidade":2.659}
{"nome":"Joe Maggio","genero":2,"popularidade":2.744}
{"nome":"Glen Morgan","genero":2,"popularidade":2.748}
{"nome":"Sophia Takal","genero":1,"popularidade":5.212}
{"nome":"Tom Paton","genero":0,"popularidade":2.744}
{"nome":"Mario Bava","genero":2,"popularidade":5.215}
{"nome":"Salvatore Billitteri","genero":0,"popularidade":1.263}
{"nome":"Jonathan King","genero":0,"popularidade":2.744}
{"nome":"Gabriel Bologna","genero":2,"popularidade":2.046}
{"nome":"William Crain","genero":2,"popularidade":3.169}
{"nome":"William Cain","genero":2,"popularidade":7.113}
{"nome":"Guillermo del Toro","genero":2,"popularidade":11.693}
{"nome":"Eduardo S\u00e1nchez","genero":2,"popularidade":6.446}
{"nome":"Tripp Rhame","genero":0,"popularidade":0.6}
{"nome":"Katja von Garnier","genero":1,"popularidade":4.187}
{"nome":"Owen Egerton","genero":2,"popularidade":1.186}
{"nome":"Jeff Kopas","genero":2,"popularidade":1.388}
{"nome":"Patrick von Barkenberg","genero":0,"popularidade":0.6}
{"nome":"Jeff Barnaby","genero":2,"popularidade":1.589}
{"nome":"Vicente Aranda","genero":2,"popularidade":4.113}
{"nome":"Justin Dix","genero":2,"popularidade":2.869}
{"nome":"Henry Jacobson","genero":2,"popularidade":1.4}
{"nome":"Ed Hunt","genero":2,"popularidade":1.556}
{"nome":"Jeff Lieberman","genero":2,"popularidade":6.038}
{"nome":"Jeff Wadlow","genero":2,"popularidade":5.113}
{"nome":"Boaz Yakin","genero":2,"popularidade":8.866}
{"nome":"Malik Vitthal","genero":2,"popularidade":7.531}
{"nome":"Jason Wulfsohn","genero":2,"popularidade":0.736}
{"nome":"S. Craig Zahler","genero":2,"popularidade":2.857}
{"nome":"Stephen Kay","genero":0,"popularidade":0.6}
{"nome":"Stewart Sparke","genero":2,"popularidade":1.96}
{"nome":"Joe Berlinger","genero":2,"popularidade":2.209}
{"nome":"John McNaughton","genero":2,"popularidade":3.884}
{"nome":"Wallace Fox","genero":2,"popularidade":5.555}
{"nome":"Mitzi Peirone","genero":1,"popularidade":1.4}
{"nome":"Adam Simon","genero":2,"popularidade":1.339}
{"nome":"John J. Flynn Jr.","genero":2,"popularidade":0.828}
{"nome":"Rian Johnson","genero":2,"popularidade":15.023}
{"nome":"Ronny Yu","genero":2,"popularidade":6.427}
{"nome":"Curt Siodmak","genero":2,"popularidade":2.974}
{"nome":"Edward D. Wood Jr.","genero":2,"popularidade":1.492}
{"nome":"David Yarovesky","genero":2,"popularidade":4.912}
{"nome":"Bernard McEveety","genero":2,"popularidade":5.214}
{"nome":"Don Coscarelli","genero":2,"popularidade":5.267}
{"nome":"Fran Rubel Kuzui","genero":1,"popularidade":1.167}
{"nome":"Sidney Hayers","genero":2,"popularidade":3.192}
{"nome":"Justin Meeks","genero":2,"popularidade":1.678}
{"nome":"Duane Graves","genero":2,"popularidade":2.816}
{"nome":"Neil Jordan","genero":2,"popularidade":9.04}
{"nome":"Travis Zariwny","genero":2,"popularidade":8.331}
{"nome":"Kaare Andrews","genero":2,"popularidade":0.914}
{"nome":"Daniel Goldhaber","genero":2,"popularidade":2.664}
{"nome":"Joel Soisson","genero":2,"popularidade":5.597}
{"nome":"Andy Palmer","genero":0,"popularidade":3.823}
{"nome":"Josh Hasty","genero":0,"popularidade":1.4}
{"nome":"Bernard Rose","genero":2,"popularidade":13.865}
{"nome":"Bill Condon","genero":2,"popularidade":7.263}
{"nome":"Umberto Lenzi","genero":2,"popularidade":2.199}
{"nome":"Ruggero Deodato","genero":2,"popularidade":4.161}
{"nome":"Trey Parker","genero":2,"popularidade":9.109}
{"nome":"Roland Joff\u00e9","genero":2,"popularidade":8.547}
{"nome":"Henry King","genero":2,"popularidade":3.513}
{"nome":"Kimberly Peirce","genero":1,"popularidade":2.58}
{"nome":"Anthony DiBlasi","genero":2,"popularidade":2.568}
{"nome":"Lewis Teague","genero":2,"popularidade":3.359}
{"nome":"Jamie Patterson","genero":0,"popularidade":1.38}
{"nome":"Bruce Hunt","genero":2,"popularidade":1.96}
{"nome":"Tod Williams","genero":2,"popularidade":3.165}
{"nome":"Deon Taylor","genero":2,"popularidade":3.353}
{"nome":"David Mart\u00edn Porras","genero":0,"popularidade":1.176}
{"nome":"John V. Knowles","genero":2,"popularidade":0.6}
{"nome":"Brad Parker","genero":0,"popularidade":0.6}
{"nome":"David Keating","genero":2,"popularidade":4.274}
{"nome":"Ethan Wiley","genero":2,"popularidade":3.137}
{"nome":"Benjamin Clark","genero":0,"popularidade":0.6}
{"nome":"John Lafia","genero":2,"popularidade":5.285}
{"nome":"Lars Klevberg","genero":2,"popularidade":1.828}
{"nome":"Jim Wynorski","genero":2,"popularidade":3.903}
{"nome":"Lewis Jackson","genero":2,"popularidade":1.788}
{"nome":"Josh Trank","genero":2,"popularidade":2.875}
{"nome":"David Twohy","genero":2,"popularidade":7.366}
{"nome":"Douglas Cheek","genero":2,"popularidade":2.057}
{"nome":"Aaron Hann","genero":2,"popularidade":1.4}
{"nome":"Mario Miscione","genero":2,"popularidade":1.22}
{"nome":"Mark L. Lester","genero":2,"popularidade":2.472}
{"nome":"Richard W. Haines","genero":2,"popularidade":1.416}
{"nome":"Lloyd Kaufman","genero":2,"popularidade":6.872}
{"nome":"Richard Haines","genero":0,"popularidade":0.6}
{"nome":"Jon Watts","genero":2,"popularidade":17.041}
{"nome":"Aaron Mirtes","genero":2,"popularidade":5.254}
{"nome":"Tom Nagel","genero":2,"popularidade":2.066}
{"nome":"Matthias Hoene","genero":0,"popularidade":3.181}
{"nome":"Richard Stanley","genero":2,"popularidade":6.789}
{"nome":"Buddy Giovinazzo","genero":2,"popularidade":1.949}
{"nome":"Paul Leyden","genero":2,"popularidade":5.289}
{"nome":"Makinov","genero":2,"popularidade":0.6}
{"nome":"Francis Lawrence","genero":2,"popularidade":6.974}
{"nome":"Luigi Cozzi","genero":2,"popularidade":1.667}
{"nome":"Eric England","genero":2,"popularidade":4.445}
{"nome":"Josh Forbes","genero":0,"popularidade":1.96}
{"nome":"Cary Murnion","genero":2,"popularidade":1.989}
{"nome":"Jonathan Milott","genero":2,"popularidade":4.445}
{"nome":"Patrick Brice","genero":2,"popularidade":5.145}
{"nome":"Justin Dec","genero":2,"popularidade":2.26}
{"nome":"Robin Hardy","genero":2,"popularidade":4.601}
{"nome":"Andrew Fleming","genero":2,"popularidade":4.593}
{"nome":"Eriq La Salle","genero":2,"popularidade":8.597}
{"nome":"Fred Andrews","genero":2,"popularidade":1.758}
{"nome":"Freddie Francis","genero":2,"popularidade":5.284}
{"nome":"Michael Gornick","genero":2,"popularidade":6.709}
{"nome":"Stephen Herek","genero":2,"popularidade":6.47}
{"nome":"Mick Garris","genero":2,"popularidade":3.462}
{"nome":"Mick Harris","genero":0,"popularidade":0.6}
{"nome":"Kristine Peterson","genero":1,"popularidade":3.231}
{"nome":"Bobby Miller","genero":2,"popularidade":3.753}
{"nome":"Dan Gildark","genero":0,"popularidade":1.849}
{"nome":"Jonas Govaerts","genero":2,"popularidade":3.592}
{"nome":"Don Mancini","genero":2,"popularidade":10.072}
{"nome":"Richard Ciupka","genero":2,"popularidade":0.84}
{"nome":"Dan Rosen","genero":2,"popularidade":1.1}
{"nome":"Kiyoshi Kurosawa","genero":2,"popularidade":5.116}
{"nome":"David Jacobson","genero":2,"popularidade":2.305}
{"nome":"Vikram Bhatt","genero":2,"popularidade":2.345}
{"nome":"Adam Egypt Mortimer","genero":2,"popularidade":1.62}
{"nome":"Ariel Vromen","genero":2,"popularidade":2.701}
{"nome":"Alex Proyas","genero":2,"popularidade":5.102}
{"nome":"Carl Strathie","genero":0,"popularidade":0.6}
{"nome":"Frank De Felitta","genero":2,"popularidade":1.634}
{"nome":"Edward Evers-Swindell","genero":0,"popularidade":1.4}
{"nome":"Marina de Van","genero":1,"popularidade":2.408}
{"nome":"Walter Salles","genero":2,"popularidade":2.77}
{"nome":"Jonathan Liebesman","genero":2,"popularidade":1.989}
{"nome":"Pollyanna McIntosh","genero":1,"popularidade":4.599}
{"nome":"Mickey Keating","genero":2,"popularidade":0.83}
{"nome":"Zack Snyder","genero":2,"popularidade":10.578}
{"nome":"H\u00e8ctor Hern\u00e1ndez Vicens","genero":2,"popularidade":1.4}
{"nome":"Pearry Reginald Teo","genero":2,"popularidade":1.4}
{"nome":"Peter Spierig","genero":2,"popularidade":4.358}
{"nome":"Michael Spierig","genero":2,"popularidade":4.543}
{"nome":"Kevin Munroe","genero":2,"popularidade":3.159}
{"nome":"Gary Sherman","genero":2,"popularidade":3.017}
{"nome":"Phillip Guzman","genero":2,"popularidade":3.044}
{"nome":"Chris Bavota","genero":0,"popularidade":1.064}
{"nome":"Lee Paula Springer","genero":0,"popularidade":0.6}
{"nome":"Brad Baruh","genero":2,"popularidade":7.267}
{"nome":"Arthur Penn","genero":2,"popularidade":3.002}
{"nome":"James Wan","genero":2,"popularidade":24.894}
{"nome":"Tommy Wirkola","genero":2,"popularidade":5.01}
{"nome":"Chris Helton","genero":0,"popularidade":1.96}
{"nome":"Tony West","genero":0,"popularidade":0.828}
{"nome":"Harrison Smith","genero":0,"popularidade":0.6}
{"nome":"Robert Rodriguez","genero":2,"popularidade":11.383}
{"nome":"Quentin Tarantino","genero":2,"popularidade":23.161}
{"nome":"Jason Lei Howden","genero":2,"popularidade":1.4}
{"nome":"Dario Piana","genero":2,"popularidade":1.22}
{"nome":"Noboru Iguchi","genero":2,"popularidade":6.605}
{"nome":"Darin Scott","genero":2,"popularidade":1.4}
{"nome":"John Pogue","genero":2,"popularidade":3.744}
{"nome":"Johnny Martin","genero":2,"popularidade":5.989}
{"nome":"Scott Derrickson","genero":2,"popularidade":5.358}
{"nome":"Brian Netto","genero":2,"popularidade":0.838}
{"nome":"Zak Bagans","genero":2,"popularidade":2.395}
{"nome":"Donald Cammell","genero":2,"popularidade":3.079}
{"nome":"Till Kleinert","genero":2,"popularidade":1.813}
{"nome":"Neil Marshall","genero":2,"popularidade":11.363}
{"nome":"Richard Greenberg","genero":2,"popularidade":0.992}
{"nome":"Fritz Lang","genero":2,"popularidade":11.962}
{"nome":"Joseph Kahn","genero":2,"popularidade":2.37}
{"nome":"Alex Craig Mann","genero":2,"popularidade":1.426}
{"nome":"Taylor Hackford","genero":2,"popularidade":4.025}
{"nome":"Adam Mason","genero":2,"popularidade":4.558}
{"nome":"Matt Bettinelli-Olpin","genero":2,"popularidade":2.506}
{"nome":"Tyler Gillett","genero":2,"popularidade":4.41}
{"nome":"Michael Mongillo","genero":0,"popularidade":0.788}
{"nome":"Craig R. Baxley","genero":2,"popularidade":5.391}
{"nome":"Silvio Narizzano","genero":2,"popularidade":1.393}
{"nome":"Daniel Haller","genero":2,"popularidade":3.107}
{"nome":"Hunter Adams","genero":0,"popularidade":3.003}
{"nome":"David Nutter","genero":0,"popularidade":0.6}
{"nome":"Richard Burton","genero":2,"popularidade":13.265}
{"nome":"Nevill Coghill","genero":0,"popularidade":1.176}
{"nome":"Troy Nixey","genero":2,"popularidade":1.204}
{"nome":"Federico \u00c1lvarez","genero":0,"popularidade":0.6}
{"nome":"Joseph Ellison","genero":2,"popularidade":1.802}
{"nome":"Alexis Wajsbrot","genero":0,"popularidade":0.6}
{"nome":"Damien Mac\u00e9","genero":0,"popularidade":0.6}
{"nome":"Mike Mendez","genero":2,"popularidade":2.39}
{"nome":"Caradog W. James","genero":0,"popularidade":0.6}
{"nome":"Nicolas Roeg","genero":2,"popularidade":3.041}
{"nome":"Rick Bieber","genero":0,"popularidade":0.6}
{"nome":"Andrzej Bartkowiak","genero":2,"popularidade":7.831}
{"nome":"Tony Giglio","genero":2,"popularidade":2.835}
{"nome":"Roy Ward Baker","genero":2,"popularidade":3.244}
{"nome":"Robert Fuest","genero":2,"popularidade":3.685}
{"nome":"Patrick Lussier","genero":2,"popularidade":4.663}
{"nome":"Alan Gibson","genero":2,"popularidade":2.175}
{"nome":"Lambert Hillyer","genero":2,"popularidade":5.453}
{"nome":"Ho-Cheung Pang","genero":0,"popularidade":0.6}
{"nome":"Lawrence Kasdan","genero":2,"popularidade":2.759}
{"nome":"Joseph Ruben","genero":2,"popularidade":2.9}
{"nome":"Chris von Hoffmann","genero":2,"popularidade":0.6}
{"nome":"Glenn Payne","genero":2,"popularidade":0.733}
{"nome":"Tomm Jacobsen","genero":2,"popularidade":2.647}
{"nome":"Michael Rousselet","genero":0,"popularidade":4.807}
{"nome":"Jody Dwyer","genero":0,"popularidade":0.688}
{"nome":"Chad Ferrin","genero":2,"popularidade":3.618}
{"nome":"Chuck Parello","genero":0,"popularidade":1.473}
{"nome":"Boris Rodriguez","genero":0,"popularidade":2.588}
{"nome":"James Watkins","genero":2,"popularidade":8.703}
{"nome":"Franck Vestiel","genero":0,"popularidade":0.6}
{"nome":"David J. Burke","genero":2,"popularidade":2.155}
{"nome":"Arch Hall Jr.","genero":2,"popularidade":2.481}
{"nome":"Arch Hall Sr.","genero":2,"popularidade":2.835}
{"nome":"Ellory Elkayem","genero":2,"popularidade":4.283}
{"nome":"Ryan Andrews","genero":0,"popularidade":0.98}
{"nome":"Robert Legato","genero":2,"popularidade":1.831}
{"nome":"Christopher Borrelli","genero":2,"popularidade":2.474}
{"nome":"James Signorelli","genero":2,"popularidade":1.371}
{"nome":"Sam Irvin","genero":2,"popularidade":3.113}
{"nome":"Carl Bessai","genero":2,"popularidade":3.073}
{"nome":"Carles Torrens","genero":2,"popularidade":1.035}
{"nome":"Bert I. Gordon","genero":2,"popularidade":3.9}
{"nome":"Peter Hyams","genero":2,"popularidade":5.167}
{"nome":"Wolfgang Petersen","genero":2,"popularidade":7.057}
{"nome":"Minos Nikolakakis","genero":0,"popularidade":0.6}
{"nome":"David Lynch","genero":2,"popularidade":9.137}
{"nome":"Paul Urkijo Alijo","genero":2,"popularidade":1.586}
{"nome":"Randy Moore","genero":2,"popularidade":6.649}
{"nome":"Patrick McGuinn","genero":2,"popularidade":2.203}
{"nome":"Werner Herzog","genero":2,"popularidade":7.588}
{"nome":"Matt Green","genero":0,"popularidade":2.379}
{"nome":"Eric Weston","genero":2,"popularidade":1.624}
{"nome":"Stuart Hazeldine","genero":2,"popularidade":1.688}
{"nome":"Richard Bates","genero":0,"popularidade":0.98}
{"nome":"William Peter Blatty","genero":2,"popularidade":7.948}
{"nome":"John Boorman","genero":2,"popularidade":5.096}
{"nome":"Blake Edwards","genero":2,"popularidade":4.483}
{"nome":"Miguel \u00c1ngel Vivas","genero":2,"popularidade":2.268}
{"nome":"Ray Xue","genero":0,"popularidade":0.6}
{"nome":"Colin Minihan","genero":2,"popularidade":6.003}
{"nome":"Irvin Kershner","genero":2,"popularidade":6.173}
{"nome":"Georges Franju","genero":2,"popularidade":1.898}
{"nome":"Johannes Roberts","genero":2,"popularidade":7.387}
{"nome":"Julien Magnat","genero":2,"popularidade":1.404}
{"nome":"Brian A. Metcalf","genero":0,"popularidade":1.566}
{"nome":"Jon Keeyes","genero":2,"popularidade":6.117}
{"nome":"Klaus Menzel","genero":2,"popularidade":2.682}
{"nome":"Adam Brooks","genero":2,"popularidade":3.207}
{"nome":"Jeremy Gillespie","genero":2,"popularidade":2.828}
{"nome":"Conor Sweeney","genero":0,"popularidade":0.84}
{"nome":"Matthew Kennedy","genero":2,"popularidade":2.562}
{"nome":"Frank LaLoggia","genero":2,"popularidade":1.558}
{"nome":"Nicolas Winding Refn","genero":2,"popularidade":7.701}
{"nome":"John Gulager","genero":2,"popularidade":1.926}
{"nome":"Jason Banker","genero":2,"popularidade":0.668}
{"nome":"Jon Knautz","genero":2,"popularidade":3.874}
{"nome":"Mark Young","genero":2,"popularidade":2.842}
{"nome":"Andrew Currie","genero":2,"popularidade":0.74}
{"nome":"Marshall Thompson","genero":2,"popularidade":4.571}
{"nome":"Arthur Crabtree","genero":0,"popularidade":2.317}
{"nome":"Graham Baker","genero":2,"popularidade":5.249}
{"nome":"James Wong","genero":2,"popularidade":10.179}
{"nome":"David R. Ellis","genero":2,"popularidade":4.194}
{"nome":"Steven Quale","genero":2,"popularidade":3.173}
{"nome":"Jimmy Huston","genero":2,"popularidade":1.32}
{"nome":"Andrew Davis","genero":2,"popularidade":3.402}
{"nome":"Robert Resnikoff","genero":0,"popularidade":1.388}
{"nome":"Arch Oboler","genero":2,"popularidade":0.969}
{"nome":"Niels Arden Oplev","genero":2,"popularidade":2.196}
{"nome":"Jeffrey Bloom","genero":2,"popularidade":2.82}
{"nome":"Rupert Wainwright","genero":2,"popularidade":3.041}
{"nome":"Antoine Le","genero":2,"popularidade":0.6}
{"nome":"Allan Holzman","genero":0,"popularidade":2.103}
{"nome":"J.S. Cardone","genero":2,"popularidade":0.84}
{"nome":"Scott Schirmer","genero":2,"popularidade":0.69}
{"nome":"Bill Paxton","genero":2,"popularidade":16.233}
{"nome":"Roy William Neill","genero":2,"popularidade":2.988}
{"nome":"Richard Raaphorst","genero":2,"popularidade":1.166}
{"nome":"Paddy Breathnach","genero":2,"popularidade":8.285}
{"nome":"Zach Lipovsky","genero":2,"popularidade":9.362}
{"nome":"John Simpson","genero":2,"popularidade":3.044}
{"nome":"Joe Hoffman","genero":0,"popularidade":0.6}
{"nome":"Danny Steinmann","genero":2,"popularidade":1.412}
{"nome":"Tom McLoughlin","genero":2,"popularidade":2.954}
{"nome":"John Carl Buechler","genero":2,"popularidade":4.921}
{"nome":"Rob Hedden","genero":2,"popularidade":3.061}
{"nome":"Marcus Nispel","genero":2,"popularidade":6.087}
{"nome":"Simon Verhoeven","genero":2,"popularidade":4.413}
{"nome":"Craig Gillespie","genero":2,"popularidade":6.507}
{"nome":"George McCowan","genero":2,"popularidade":4.475}
{"nome":"Kevin Connor","genero":2,"popularidade":4.176}
{"nome":"Scott Spiegel","genero":2,"popularidade":3.646}
{"nome":"Allen Hughes","genero":2,"popularidade":2.529}
{"nome":"Albert Hughes","genero":2,"popularidade":7.875}
{"nome":"Xavier Gens","genero":2,"popularidade":2.763}
{"nome":"Sarah Kelly","genero":0,"popularidade":1.205}
{"nome":"Clive Saunders","genero":0,"popularidade":0.6}
{"nome":"Adam Krause","genero":0,"popularidade":1.495}
{"nome":"S\u00e9bastien Landry","genero":2,"popularidade":0.6}
{"nome":"Bill Gunn","genero":2,"popularidade":2.638}
{"nome":"Tibor Tak\u00e1cs","genero":2,"popularidade":5.725}
{"nome":"Michael Thomas Daniel","genero":2,"popularidade":0.6}
{"nome":"Olivier Abbou","genero":2,"popularidade":1.62}
{"nome":"Jordan Peele","genero":2,"popularidade":9.34}
{"nome":"Fabr\u00edcio Bittar","genero":2,"popularidade":0.652}
{"nome":"John Stimpson","genero":2,"popularidade":1.855}
{"nome":"Erle C. Kenton","genero":2,"popularidade":1.12}
{"nome":"Mark Steven Johnson","genero":2,"popularidade":5.071}
{"nome":"Steve Beck","genero":2,"popularidade":3.732}
{"nome":"Zoya Akhtar","genero":1,"popularidade":6.091}
{"nome":"Anurag Kashyap","genero":2,"popularidade":4.369}
{"nome":"Dibakar Banerjee","genero":2,"popularidade":2.779}
{"nome":"Karan Johar","genero":2,"popularidade":2.862}
{"nome":"John Irvin","genero":2,"popularidade":2.524}
{"nome":"Ben Peyser","genero":2,"popularidade":1.96}
{"nome":"Scott Rutherford","genero":2,"popularidade":1.79}
{"nome":"Eric Bress","genero":2,"popularidade":7.221}
{"nome":"Albert Band","genero":2,"popularidade":4.72}
{"nome":"Ray Kellogg","genero":2,"popularidade":3.348}
{"nome":"Charles Band","genero":2,"popularidade":5.346}
{"nome":"Travis Stevens","genero":2,"popularidade":2.584}
{"nome":"Catherine Hardwicke","genero":1,"popularidade":5.557}
{"nome":"Stephen Poliakoff","genero":2,"popularidade":1.865}
{"nome":"Nick Hamm","genero":2,"popularidade":1.4}
{"nome":"Roland Emmerich","genero":2,"popularidade":6.163}
{"nome":"Takao Okawara","genero":2,"popularidade":4.619}
{"nome":"Jun Fukuda","genero":2,"popularidade":2.467}
{"nome":"Koichi Kawakita","genero":2,"popularidade":2.367}
{"nome":"Kensho Yamashita","genero":0,"popularidade":2.723}
{"nome":"Paul Wegener","genero":2,"popularidade":2.568}
{"nome":"Carl Boese","genero":2,"popularidade":2.033}
{"nome":"Veronika Franz","genero":1,"popularidade":1.395}
{"nome":"Severin Fiala","genero":2,"popularidade":2.615}
{"nome":"Rob Letterman","genero":2,"popularidade":4.445}
{"nome":"Ari Sandel","genero":2,"popularidade":1.395}
{"nome":"Mathieu Kassovitz","genero":2,"popularidade":12.951}
{"nome":"Jon Wright","genero":2,"popularidade":2.343}
{"nome":"Herb Freed","genero":2,"popularidade":3.087}
{"nome":"Stuart Ortiz","genero":0,"popularidade":4.654}
{"nome":"John Poliquin","genero":2,"popularidade":1.572}
{"nome":"James Rodriguez","genero":0,"popularidade":1.182}
{"nome":"Jeremy Saulnier","genero":2,"popularidade":6.227}
{"nome":"Kinji Fukasaku","genero":2,"popularidade":5.902}
{"nome":"Graham Denman","genero":0,"popularidade":2.276}
{"nome":"Takashi Shimizu","genero":2,"popularidade":5.32}
{"nome":"Elias","genero":0,"popularidade":0.6}
{"nome":"Lukas Feigelfeld","genero":2,"popularidade":1.094}
{"nome":"Miles Doleac","genero":2,"popularidade":8.766}
{"nome":"David Gordon Green","genero":2,"popularidade":17.472}
{"nome":"Mark Cullingham","genero":2,"popularidade":2.317}
{"nome":"Dominique Othenin-Girard","genero":2,"popularidade":1.794}
{"nome":"Rick Rosenthal","genero":2,"popularidade":6.499}
{"nome":"Tommy Lee Wallace","genero":2,"popularidade":4.966}
{"nome":"Rick Rosenthal","genero":2,"popularidade":6.499}
{"nome":"Daniel Simpson","genero":2,"popularidade":0.732}
{"nome":"Adam Mason","genero":2,"popularidade":4.558}
{"nome":"Peter Webber","genero":2,"popularidade":1.907}
{"nome":"Duane Journey","genero":0,"popularidade":1.517}
{"nome":"Takashi Miike","genero":2,"popularidade":11.539}
{"nome":"J. Lee Thompson","genero":2,"popularidade":6.115}
{"nome":"Alec Gillis","genero":2,"popularidade":6.276}
{"nome":"David Slade","genero":2,"popularidade":4.267}
{"nome":"Richard Stanley","genero":2,"popularidade":6.789}
{"nome":"Keith Wright","genero":2,"popularidade":1.96}
{"nome":"Rob Grant","genero":0,"popularidade":1.735}
{"nome":"Adam Green","genero":2,"popularidade":4.185}
{"nome":"Mario Bava","genero":2,"popularidade":5.215}
{"nome":"Mac Carter","genero":0,"popularidade":0.671}
{"nome":"Scott Beck","genero":2,"popularidade":5.039}
{"nome":"Bryan Woods","genero":2,"popularidade":6.507}
{"nome":"Victor Salva","genero":2,"popularidade":7.861}
{"nome":"Rob Minkoff","genero":2,"popularidade":7.226}
{"nome":"Roger Corman","genero":2,"popularidade":9.516}
{"nome":"Rob Zombie","genero":2,"popularidade":7.51}
{"nome":"Mr. Lawrence","genero":2,"popularidade":8.452}
{"nome":"Vincenzo Natali","genero":2,"popularidade":8.026}
{"nome":"Jon Schnitzer","genero":0,"popularidade":0.6}
{"nome":"Benjamin Christensen","genero":2,"popularidade":2.218}
{"nome":"Elle Callahan","genero":1,"popularidade":1.4}
{"nome":"Andrew van den Houten","genero":2,"popularidade":1.4}
{"nome":"Philip Ridley","genero":2,"popularidade":2.694}
{"nome":"Robert Ben Garant","genero":2,"popularidade":7.815}
{"nome":"Thomas Lennon","genero":2,"popularidade":18.72}
{"nome":"Gregory Plotkin","genero":2,"popularidade":1.821}
{"nome":"Stephen Cognetti","genero":0,"popularidade":2.575}
{"nome":"J.T. Petty","genero":2,"popularidade":3.185}
{"nome":"Tony Randel","genero":2,"popularidade":6.672}
{"nome":"Guillermo del Toro","genero":2,"popularidade":11.693}
{"nome":"Bruce McDonald","genero":2,"popularidade":4.55}
{"nome":"Clive Barker","genero":2,"popularidade":4.433}
{"nome":"Alan Smithee","genero":2,"popularidade":6.426}
{"nome":"Kevin Yagher","genero":2,"popularidade":6.124}
{"nome":"Rick Bota","genero":2,"popularidade":6.783}
{"nome":"Anthony Hickox","genero":2,"popularidade":4.256}
{"nome":"Gary J. Tunnicliffe","genero":2,"popularidade":2.968}
{"nome":"John McNaughton","genero":2,"popularidade":3.884}
{"nome":"Ari Aster","genero":2,"popularidade":14.661}
{"nome":"John Borowski","genero":2,"popularidade":2.579}
{"nome":"Jack Sholder","genero":2,"popularidade":7.757}
{"nome":"Matt Duffer","genero":2,"popularidade":4.154}
{"nome":"Ross Duffer","genero":2,"popularidade":4.649}
{"nome":"K.C. Bascombe","genero":0,"popularidade":1.4}
{"nome":"Alexandre Aja","genero":2,"popularidade":5.536}
{"nome":"Martin Weisz","genero":2,"popularidade":3.732}
{"nome":"Wes Craven","genero":2,"popularidade":6.705}
{"nome":"Dave Meyers","genero":2,"popularidade":2.215}
{"nome":"David Burns","genero":2,"popularidade":6.226}
{"nome":"Jeff Vigil","genero":0,"popularidade":1.96}
{"nome":"Jeremy Berg","genero":0,"popularidade":1.62}
{"nome":"Jeff Ferrell","genero":0,"popularidade":1.176}
{"nome":"Michael Axelgaard","genero":0,"popularidade":1.96}
{"nome":"Paul Verhoeven","genero":2,"popularidade":7.541}
{"nome":"Claudio F\u00e4h","genero":2,"popularidade":8.887}
{"nome":"William Castle","genero":2,"popularidade":3.353}
{"nome":"Tara Subkoff","genero":1,"popularidade":6.645}
{"nome":"Eugenio Mart\u00edn","genero":2,"popularidade":4.534}
{"nome":"Terence Fisher","genero":2,"popularidade":2.129}
{"nome":"Jonas \u00c5kerlund","genero":2,"popularidade":3.357}
{"nome":"Eli Roth","genero":2,"popularidade":16.319}
{"nome":"Scott Spiegel","genero":2,"popularidade":3.646}
{"nome":"Mathieu Turi","genero":2,"popularidade":1.012}
{"nome":"Mike Figgis","genero":2,"popularidade":4.501}
{"nome":"Ingmar Bergman","genero":2,"popularidade":14.828}
{"nome":"Ethan Wiley","genero":2,"popularidade":3.137}
{"nome":"Fritz Lang","genero":2,"popularidade":11.962}
{"nome":"Dan Curtis","genero":2,"popularidade":5.265}
{"nome":"Erle C. Kenton","genero":2,"popularidade":1.12}
{"nome":"Alfredo Leone","genero":0,"popularidade":1.078}
{"nome":"Jaume Collet-Serra","genero":2,"popularidade":6.14}
{"nome":"Mark Rosman","genero":2,"popularidade":8.065}
{"nome":"Paul Schiff","genero":2,"popularidade":3.244}
{"nome":"Alastair Orr","genero":2,"popularidade":1.4}
{"nome":"Peter Duffell","genero":2,"popularidade":0.827}
{"nome":"Joe Dante","genero":2,"popularidade":4.081}
{"nome":"Philippe Mora","genero":2,"popularidade":4.753}
{"nome":"Joe Nimziki","genero":2,"popularidade":2.92}
{"nome":"Tom Six","genero":2,"popularidade":4.484}
{"nome":"Peter Sasdy","genero":2,"popularidade":1.846}
{"nome":"Barbara Peeters","genero":1,"popularidade":1.4}
{"nome":"Mike Flanagan","genero":2,"popularidade":4.52}
{"nome":"Robert Aldrich","genero":2,"popularidade":6.687}
{"nome":"Oz Perkins","genero":2,"popularidade":7.028}
{"nome":"Albert Band","genero":2,"popularidade":4.72}
{"nome":"Graham Reznick","genero":2,"popularidade":5.622}
{"nome":"Craig R. Baxley","genero":2,"popularidade":5.391}
{"nome":"Stuart Beattie","genero":2,"popularidade":6.078}
{"nome":"Jim Gillespie","genero":2,"popularidade":4.109}
{"nome":"Ren\u00e9 Clair","genero":2,"popularidade":6.388}
{"nome":"Meir Zarchi","genero":2,"popularidade":1.141}
{"nome":"Steven R. Monroe","genero":2,"popularidade":4.42}
{"nome":"Danny Cannon","genero":2,"popularidade":4.421}
{"nome":"Josh Lobo","genero":2,"popularidade":0.6}
{"nome":"Jacques Tourneur","genero":2,"popularidade":4.822}
{"nome":"John Elias Michalakis","genero":0,"popularidade":0.6}
{"nome":"Mark Edwin Robinson","genero":0,"popularidade":1.631}
{"nome":"Eric Stanze","genero":2,"popularidade":0.652}
{"nome":"Chad Archibald","genero":2,"popularidade":2.659}
{"nome":"Robert Altman","genero":2,"popularidade":6.261}
{"nome":"Walerian Borowczyk","genero":2,"popularidade":3.662}
{"nome":"Po-Chih Leong","genero":2,"popularidade":1.362}
{"nome":"Neil Jordan","genero":2,"popularidade":9.04}
{"nome":"Peter Strickland","genero":2,"popularidade":3.576}
{"nome":"Allen Wolf","genero":2,"popularidade":2.744}
{"nome":"John Carpenter","genero":2,"popularidade":13.512}
{"nome":"Alex Chandon","genero":2,"popularidade":1.313}
{"nome":"Brad Peyton","genero":2,"popularidade":5.186}
{"nome":"Pascal Laugier","genero":2,"popularidade":7.733}
{"nome":"Jack Arnold","genero":2,"popularidade":7.258}
{"nome":"Dario Argento","genero":2,"popularidade":9.252}
{"nome":"Seth Grossman","genero":2,"popularidade":1.304}
{"nome":"John Landis","genero":2,"popularidade":8.039}
{"nome":"Alexandre Bustillo","genero":2,"popularidade":3.195}
{"nome":"Julien Maury","genero":2,"popularidade":4.187}
{"nome":"Miguel \u00c1ngel Vivas","genero":2,"popularidade":2.268}
{"nome":"James Wan","genero":2,"popularidade":24.894}
{"nome":"Leigh Whannell","genero":2,"popularidade":6.889}
{"nome":"Adam Robitel","genero":2,"popularidade":7.493}
{"nome":"Neil Burger","genero":2,"popularidade":5.663}
{"nome":"David Bailey","genero":0,"popularidade":2.423}
{"nome":"Travis Zariwny","genero":2,"popularidade":8.331}
{"nome":"Juan Carlos Fresnadillo","genero":2,"popularidade":2.789}
{"nome":"Adam Schindler","genero":0,"popularidade":0.6}
{"nome":"Oliver Hirschbiegel","genero":2,"popularidade":2.899}
{"nome":"Denis Sanders","genero":2,"popularidade":3.753}
{"nome":"Mark Robson","genero":2,"popularidade":2.449}
{"nome":"Andy Muschietti","genero":2,"popularidade":7.76}
{"nome":"Robert Gordon","genero":2,"popularidade":2.554}
{"nome":"Marko M\u00e4kilaakso","genero":2,"popularidade":2.187}
{"nome":"Trey Edward Shults","genero":2,"popularidade":1.96}
{"nome":"David Robert Mitchell","genero":2,"popularidade":3.335}
{"nome":"Larry Cohen","genero":2,"popularidade":2.704}
{"nome":"Colin Minihan","genero":2,"popularidade":6.003}
{"nome":"Edward L. Cahn","genero":2,"popularidade":3.111}
{"nome":"Michael Gallo","genero":0,"popularidade":0.6}
{"nome":"Bradley Rust Gray","genero":2,"popularidade":0.6}
{"nome":"Jon Knautz","genero":2,"popularidade":3.874}
{"nome":"Kevin Greutert","genero":2,"popularidade":14.081}
{"nome":"John Maybury","genero":2,"popularidade":1.444}
{"nome":"Adrian Lyne","genero":2,"popularidade":10.732}
{"nome":"David M. Rosenthal","genero":2,"popularidade":1.586}
{"nome":"Adam Marcus","genero":2,"popularidade":3.332}
{"nome":"James Isaac","genero":2,"popularidade":4.056}
{"nome":"Joe Alves","genero":2,"popularidade":3.407}
{"nome":"Joseph Sargent","genero":2,"popularidade":5.147}
{"nome":"Arthur Marks","genero":2,"popularidade":3.962}
{"nome":"Karyn Kusama","genero":1,"popularidade":4.266}
{"nome":"Paul Tarnopol","genero":0,"popularidade":2.476}
{"nome":"Lee Demarbre","genero":0,"popularidade":7.74}
{"nome":"Michael Spierig","genero":2,"popularidade":4.543}
{"nome":"Peter Spierig","genero":2,"popularidade":4.358}
{"nome":"Ajmal Zaheer Ahmad","genero":2,"popularidade":0.6}
{"nome":"Mark Atkins","genero":2,"popularidade":2.538}
{"nome":"Don Coscarelli","genero":2,"popularidade":5.267}
{"nome":"Simon Rumley","genero":2,"popularidade":1.027}
{"nome":"Jimmy Hayward","genero":2,"popularidade":4.882}
{"nome":"Declan O'Brien","genero":2,"popularidade":2.853}
{"nome":"Alejandro Brugu\u00e9s","genero":2,"popularidade":5.202}
{"nome":"Chad Crawford Kinkle","genero":0,"popularidade":0.6}
{"nome":"Michael Mann","genero":2,"popularidade":13.589}
{"nome":"Ben Wheatley","genero":2,"popularidade":8.169}
{"nome":"Elliot Feld","genero":0,"popularidade":1.905}
{"nome":"Stephen Chiodo","genero":2,"popularidade":2.248}
{"nome":"Zachary Hansen","genero":0,"popularidade":0.98}
{"nome":"Ray Kellogg","genero":2,"popularidade":3.348}
{"nome":"Don Sharp","genero":2,"popularidade":2.448}
{"nome":"Daniel Liatowitsch","genero":0,"popularidade":1.435}
{"nome":"David Todd Ocvirk","genero":2,"popularidade":0.6}
{"nome":"Michael Dougherty","genero":2,"popularidade":3.471}
{"nome":"Masaki Kobayashi","genero":2,"popularidade":5.327}
{"nome":"Alberto Rodr\u00edguez","genero":2,"popularidade":5.812}
{"nome":"Frank LaLoggia","genero":2,"popularidade":1.558}
{"nome":"Ken Russell","genero":2,"popularidade":5.428}
{"nome":"Steve Miner","genero":2,"popularidade":3.978}
{"nome":"George A. Romero","genero":2,"popularidade":5.741}
{"nome":"Evan Cecil","genero":0,"popularidade":0.6}
{"nome":"Daniel Stamm","genero":2,"popularidade":2.939}
{"nome":"Anthony DiBlasi","genero":2,"popularidade":2.568}
{"nome":"Larry Fessenden","genero":2,"popularidade":7.805}
{"nome":"Brett Leonard","genero":2,"popularidade":3.416}
{"nome":"Jeff Burr","genero":2,"popularidade":2.531}
{"nome":"John Hough","genero":2,"popularidade":1.915}
{"nome":"Scott Stewart","genero":0,"popularidade":0.691}
{"nome":"Richard Blackburn","genero":2,"popularidade":2.624}
{"nome":"Mark Jones","genero":2,"popularidade":0.759}
{"nome":"Rob Spera","genero":2,"popularidade":2.263}
{"nome":"Brian Trenchard-Smith","genero":2,"popularidade":2.374}
{"nome":"Steven Ayromlooi","genero":2,"popularidade":1.4}
{"nome":"Zach Lipovsky","genero":2,"popularidade":9.362}
{"nome":"Steven Kostanski","genero":2,"popularidade":9.475}
{"nome":"Phil Claydon","genero":2,"popularidade":2.307}
{"nome":"Matt Reeves","genero":2,"popularidade":15.591}
{"nome":"Tomas Alfredson","genero":2,"popularidade":10.77}
{"nome":"Owen Martin","genero":0,"popularidade":2.304}
{"nome":"John D. Hancock","genero":2,"popularidade":1.39}
{"nome":"John Hancock","genero":2,"popularidade":2.702}
{"nome":"George P. Cosmatos","genero":2,"popularidade":4.883}
{"nome":"Justin McConnell","genero":2,"popularidade":1.308}
{"nome":"Tobe Hooper","genero":2,"popularidade":4.255}
{"nome":"Robert Hall","genero":0,"popularidade":0.6}
{"nome":"David F. Sandberg","genero":2,"popularidade":4.022}
{"nome":"Robert Mockler","genero":2,"popularidade":0.6}
{"nome":"Eli Craig","genero":2,"popularidade":6.763}
{"nome":"Nicolas Gessner","genero":2,"popularidade":1.583}
{"nome":"Abe Forsythe","genero":2,"popularidade":2.372}
{"nome":"Brian A. Metcalf","genero":0,"popularidade":1.566}
{"nome":"Jamie Blanks","genero":2,"popularidade":2.949}
{"nome":"Colin Eggleston","genero":2,"popularidade":1.888}
{"nome":"Michael Crichton","genero":2,"popularidade":8.798}
{"nome":"Guillem Morales","genero":2,"popularidade":4.438}
{"nome":"Joel Schumacher","genero":2,"popularidade":3.852}
{"nome":"Dario Piana","genero":2,"popularidade":1.22}
{"nome":"David Lynch","genero":2,"popularidade":9.137}
{"nome":"Joe Johnston","genero":2,"popularidade":6.773}
{"nome":"Steven Spielberg","genero":2,"popularidade":24.334}
{"nome":"Eduardo S\u00e1nchez","genero":2,"popularidade":6.446}
{"nome":"Gonzalo Calzada","genero":0,"popularidade":0.84}
{"nome":"C. Courtney Joyner","genero":2,"popularidade":2.127}
{"nome":"Stewart Thorndike","genero":1,"popularidade":1.008}
{"nome":"Tate Taylor","genero":2,"popularidade":10.354}
{"nome":"Noboru Iguchi","genero":2,"popularidade":6.605}
{"nome":"Gregory Hatanaka","genero":2,"popularidade":2.55}
{"nome":"Jules Bass","genero":2,"popularidade":2.156}
{"nome":"Joe Giannone","genero":0,"popularidade":0.98}
{"nome":"Henry Hobson","genero":2,"popularidade":1.176}
{"nome":"Olaf de Fleur Johannesson","genero":2,"popularidade":1.4}
{"nome":"R\u00e9my Belvaux","genero":2,"popularidade":2.304}
{"nome":"Andr\u00e9 Bonzel","genero":2,"popularidade":2.712}
{"nome":"Beno\u00eet Poelvoorde","genero":2,"popularidade":6.941}
{"nome":"Carl Reiner","genero":2,"popularidade":5.292}
{"nome":"Jonathan Levine","genero":2,"popularidade":2.695}
{"nome":"Dwain Esper","genero":2,"popularidade":0.755}
{"nome":"William Lustig","genero":2,"popularidade":3.812}
{"nome":"Franck Khalfoun","genero":2,"popularidade":8.446}
{"nome":"William Girdler","genero":2,"popularidade":1.535}
{"nome":"John Lafia","genero":2,"popularidade":5.285}
{"nome":"Jim Van Bebber","genero":2,"popularidade":2.136}
{"nome":"Clive Tonge","genero":0,"popularidade":1.165}
{"nome":"Takashi Shimizu","genero":2,"popularidade":5.32}
{"nome":"Adrian Hoven","genero":2,"popularidade":4.544}
{"nome":"Michael Armstrong","genero":2,"popularidade":4.233}
{"nome":"Sergio G. S\u00e1nchez","genero":2,"popularidade":1.404}
{"nome":"Michael Goi","genero":2,"popularidade":3.185}
{"nome":"Stephen Frears","genero":2,"popularidade":6.738}
{"nome":"Kenneth Branagh","genero":2,"popularidade":35.021}
{"nome":"Stephen King","genero":2,"popularidade":18.506}
{"nome":"Lucky McKee","genero":2,"popularidade":3.063}
{"nome":"Timo Tjahjanto","genero":2,"popularidade":4.136}
{"nome":"Eric Forsberg","genero":2,"popularidade":3.245}
{"nome":"Jack Perez","genero":2,"popularidade":0.968}
{"nome":"P.J. Hogan","genero":2,"popularidade":2.478}
{"nome":"Paul Wendkos","genero":2,"popularidade":2.309}
{"nome":"Scott Leberecht","genero":2,"popularidade":0.676}
{"nome":"Rob Reiner","genero":2,"popularidade":14.26}
{"nome":"Frank Darabont","genero":2,"popularidade":11.051}
{"nome":"Brian Taylor","genero":2,"popularidade":4.206}
{"nome":"Holger Tappe","genero":2,"popularidade":1.357}
{"nome":"Chris von Hoffmann","genero":2,"popularidade":0.6}
{"nome":"Fred Dekker","genero":2,"popularidade":4.345}
{"nome":"Bruce Wemple","genero":0,"popularidade":3.952}
{"nome":"Luke Scott","genero":2,"popularidade":2.363}
{"nome":"Irving Pichel","genero":2,"popularidade":5.264}
{"nome":"Ernest B. Schoedsack","genero":2,"popularidade":2.44}
{"nome":"Kevin Connor","genero":2,"popularidade":4.176}
{"nome":"Darren Aronofsky","genero":2,"popularidade":15.969}
{"nome":"Charles Kaufman","genero":2,"popularidade":1.458}
{"nome":"Darren Lynn Bousman","genero":2,"popularidade":6.466}
{"nome":"Karl Mueller","genero":2,"popularidade":1.482}
{"nome":"Steve Wolsh","genero":0,"popularidade":1.905}
{"nome":"Jim Mickle","genero":2,"popularidade":2.492}
{"nome":"John Waters","genero":2,"popularidade":5.496}
{"nome":"Steven Sheil","genero":2,"popularidade":1.4}
{"nome":"Stephen Sommers","genero":2,"popularidade":13.2}
{"nome":"Leslie Goodwins","genero":2,"popularidade":1.306}
{"nome":"Reginald Le Borg","genero":2,"popularidade":1.276}
{"nome":"Christy Cabanne","genero":2,"popularidade":4.367}
{"nome":"Harold Young","genero":2,"popularidade":2.006}
{"nome":"Bob Clark","genero":2,"popularidade":5.262}
{"nome":"Jeremy Saulnier","genero":2,"popularidade":6.227}
{"nome":"Nick Palumbo","genero":2,"popularidade":1.4}
{"nome":"George Mihalka","genero":2,"popularidade":2.425}
{"nome":"Patrick Lussier","genero":2,"popularidade":4.663}
{"nome":"Werner Herzog","genero":2,"popularidade":7.588}
{"nome":"Dennis Bartok","genero":2,"popularidade":0.6}
{"nome":"Kiah Roache-Turner","genero":2,"popularidade":1.453}
{"nome":"Lucio Fulci","genero":2,"popularidade":9.064}
{"nome":"Paul Haggis","genero":2,"popularidade":6.81}
{"nome":"Kevin Tenney","genero":2,"popularidade":6.205}
{"nome":"Adam Gierasch","genero":2,"popularidade":1.628}
{"nome":"Tom Savini","genero":2,"popularidade":30.122}
{"nome":"Mathias Dinter","genero":2,"popularidade":3.504}
{"nome":"Brian G. Hutton","genero":2,"popularidade":3.352}
{"nome":"Timur Bekmambetov","genero":2,"popularidade":3.445}
{"nome":"Mick Garris","genero":2,"popularidade":3.462}
{"nome":"Umberto Lenzi","genero":2,"popularidade":2.199}
{"nome":"Rolfe Kanefsky","genero":2,"popularidade":2.7}
{"nome":"Samuel Bayer","genero":2,"popularidade":4.911}
{"nome":"Cornel Wilde","genero":2,"popularidade":9.813}
{"nome":"Will Wernick","genero":0,"popularidade":1.103}
{"nome":"John McTiernan","genero":2,"popularidade":6.687}
{"nome":"John McTernan","genero":0,"popularidade":1.259}
{"nome":"Jorge Grau","genero":2,"popularidade":2.916}
{"nome":"Bill Duke","genero":2,"popularidade":16.038}
{"nome":"Daniel Tucker","genero":0,"popularidade":0.6}
{"nome":"Anthony Leonardi III","genero":2,"popularidade":1.625}
{"nome":"Douglas Aarniokoski","genero":2,"popularidade":2.856}
{"nome":"Dominique Othenin-Girard","genero":2,"popularidade":1.794}
{"nome":"Howard Storm","genero":2,"popularidade":2.412}
{"nome":"Tony Barbieri","genero":0,"popularidade":3.069}
{"nome":"Eric Valette","genero":2,"popularidade":6.188}
{"nome":"Padraig Reynolds","genero":2,"popularidade":3.175}
{"nome":"Gonzalo L\u00f3pez-Gallego","genero":2,"popularidade":2.044}
{"nome":"Chris Kentis","genero":2,"popularidade":5.591}
{"nome":"Hans Horn","genero":2,"popularidade":3.144}
{"nome":"Alejandro Amen\u00e1bar","genero":2,"popularidade":8.872}
{"nome":"Michael Anderson","genero":2,"popularidade":3.409}
{"nome":"Stephen C. Apostolof","genero":2,"popularidade":1.4}
{"nome":"Edward D. Wood Jr.","genero":2,"popularidade":1.492}
{"nome":"Stiles White","genero":2,"popularidade":1.848}
{"nome":"Samuel Galli","genero":0,"popularidade":0.6}
{"nome":"Llu\u00eds Qu\u00edlez","genero":2,"popularidade":0.608}
{"nome":"Steve Barker","genero":0,"popularidade":0.6}
{"nome":"Julius Avery","genero":2,"popularidade":4.086}
{"nome":"Christian Alvart","genero":2,"popularidade":4.503}
{"nome":"Ray Milland","genero":2,"popularidade":12.481}
{"nome":"Satoshi Kon","genero":2,"popularidade":8.754}
{"nome":"Oren Peli","genero":2,"popularidade":5.271}
{"nome":"Tod Williams","genero":2,"popularidade":3.165}
{"nome":"Ariel Schulman","genero":2,"popularidade":8.13}
{"nome":"Henry Joost","genero":2,"popularidade":2.613}
{"nome":"Christopher Landon","genero":2,"popularidade":21.498}
{"nome":"Charles Band","genero":2,"popularidade":5.346}
{"nome":"Bob Balaban","genero":2,"popularidade":9.964}
{"nome":"Stefan Ruzowitzky","genero":2,"popularidade":2.873}
{"nome":"Mark Hartley","genero":2,"popularidade":4.125}
{"nome":"Jake Kennedy","genero":2,"popularidade":1.69}
{"nome":"Ramiro Garc\u00eda Bogliano","genero":0,"popularidade":0.631}
{"nome":"Eddie Alcazar","genero":0,"popularidade":1.116}
{"nome":"Stanley M. Brooks","genero":2,"popularidade":0.84}
{"nome":"Mary Lambert","genero":1,"popularidade":7.093}
{"nome":"Kevin K\u00f6lsch","genero":2,"popularidade":1.233}
{"nome":"Dennis Widmyer","genero":2,"popularidade":1.784}
{"nome":"David Hartman","genero":2,"popularidade":2.236}
{"nome":"Arthur Lubin","genero":2,"popularidade":4.71}
{"nome":"Justin Barber","genero":2,"popularidade":3.004}
{"nome":"Nick Willing","genero":2,"popularidade":1.234}
{"nome":"Juan Piquer Sim\u00f3n","genero":2,"popularidade":1.884}
{"nome":"James Cameron","genero":2,"popularidade":11.568}
{"nome":"Ovidio G. Assonitis","genero":2,"popularidade":1.497}
{"nome":"John Gulager","genero":2,"popularidade":1.926}
{"nome":"David Twohy","genero":2,"popularidade":7.366}
{"nome":"Quentin Tarantino","genero":2,"popularidade":23.161}
{"nome":"Robert Rodriguez","genero":2,"popularidade":11.383}
{"nome":"Edgar Wright","genero":2,"popularidade":13.354}
{"nome":"Michael A. Nickles","genero":2,"popularidade":3.545}
{"nome":"Daniel Robbins","genero":2,"popularidade":1.781}
{"nome":"Mickey Keating","genero":2,"popularidade":0.83}
{"nome":"Lars Klevberg","genero":2,"popularidade":1.828}
{"nome":"Gil Kenan","genero":2,"popularidade":4.619}
{"nome":"Gary Sherman","genero":2,"popularidade":3.017}
{"nome":"Gregg Hale","genero":0,"popularidade":2.097}
{"nome":"Liam O'Donnell","genero":2,"popularidade":2.721}
{"nome":"Matthew Holness","genero":2,"popularidade":3.169}
{"nome":"Uwe Boll","genero":2,"popularidade":4.735}
{"nome":"Lloyd Kaufman","genero":2,"popularidade":6.872}
{"nome":"Shane Black","genero":2,"popularidade":11.04}
{"nome":"Stephen Hopkins","genero":2,"popularidade":5.148}
{"nome":"Christopher Denham","genero":2,"popularidade":7.655}
{"nome":"Burr Steers","genero":2,"popularidade":2.523}
{"nome":"Josh Reed","genero":2,"popularidade":1.09}
{"nome":"Ridley Scott","genero":2,"popularidade":12.999}
{"nome":"Alfred Hitchcock","genero":2,"popularidade":13.767}
{"nome":"Richard Franklin","genero":2,"popularidade":5.286}
{"nome":"Anthony Perkins","genero":2,"popularidade":12.287}
{"nome":"Jim Sonzero","genero":2,"popularidade":2.341}
{"nome":"Marcus Adams","genero":0,"popularidade":0.6}
{"nome":"Kiyoshi Kurosawa","genero":2,"popularidade":5.116}
{"nome":"Stan Winston","genero":2,"popularidade":7.795}
{"nome":"David Schmoeller","genero":2,"popularidade":4.619}
{"nome":"David Allen","genero":2,"popularidade":0.98}
{"nome":"Sonny Laguna","genero":0,"popularidade":1.915}
{"nome":"Tommy Wiklund","genero":2,"popularidade":0.6}
{"nome":"Stuart Orme","genero":2,"popularidade":1.416}
{"nome":"Adam MacDonald","genero":2,"popularidade":2.325}
{"nome":"John Pogue","genero":2,"popularidade":3.744}
{"nome":"Paul Goldman","genero":2,"popularidade":2.128}
{"nome":"David Cronenberg","genero":2,"popularidade":12.039}
{"nome":"Jen Soska","genero":1,"popularidade":4.145}
{"nome":"Sylvia Soska","genero":1,"popularidade":6.419}
{"nome":"Navot Papushado","genero":2,"popularidade":1.742}
{"nome":"Jack Starrett","genero":2,"popularidade":6.66}
{"nome":"Katt Shea","genero":1,"popularidade":5.959}
{"nome":"Marvin Kren","genero":2,"popularidade":4.137}
{"nome":"Paul Middleditch","genero":2,"popularidade":1.42}
{"nome":"Antonia Bird","genero":1,"popularidade":2.125}
{"nome":"Robin Aubert","genero":2,"popularidade":3.423}
{"nome":"Julia Ducournau","genero":1,"popularidade":4.763}
{"nome":"Josh C. Waller","genero":2,"popularidade":1.202}
{"nome":"Russell Mulcahy","genero":2,"popularidade":4.095}
{"nome":"Matt Bettinelli-Olpin","genero":2,"popularidade":2.506}
{"nome":"Tyler Gillett","genero":2,"popularidade":4.41}
{"nome":"Stuart Gordon","genero":2,"popularidade":8.964}
{"nome":"Jaume Balaguer\u00f3","genero":2,"popularidade":4.028}
{"nome":"Paco Plaza","genero":2,"popularidade":8.397}
{"nome":"Brett Ratner","genero":2,"popularidade":3.705}
{"nome":"Cameron Macgowan","genero":0,"popularidade":1.882}
{"nome":"Kevin Smith","genero":2,"popularidade":8.335}
{"nome":"Peter Hyams","genero":2,"popularidade":5.167}
{"nome":"Natalie Erika James","genero":1,"popularidade":1.166}
{"nome":"Philippe Caland","genero":0,"popularidade":1.208}
{"nome":"Bob Logan","genero":0,"popularidade":3.17}
{"nome":"John Gilling","genero":2,"popularidade":2.737}
{"nome":"Poul Bang","genero":2,"popularidade":2.55}
{"nome":"Sidney W. Pink","genero":0,"popularidade":0.6}
{"nome":"Roman Polanski","genero":2,"popularidade":12.254}
{"nome":"Alexander Witt","genero":2,"popularidade":4.362}
{"nome":"Makoto Kamiya","genero":2,"popularidade":2.836}
{"nome":"Justin Benson","genero":2,"popularidade":9.849}
{"nome":"Aaron Moorhead","genero":2,"popularidade":3.201}
{"nome":"Amando de Ossorio","genero":2,"popularidade":2.975}
{"nome":"Jim Wynorski","genero":2,"popularidade":3.903}
{"nome":"Edward Bernds","genero":2,"popularidade":1.691}
{"nome":"John De Bello","genero":2,"popularidade":1.698}
{"nome":"Dan O'Bannon","genero":2,"popularidade":3.53}
{"nome":"Ken Wiederhorn","genero":2,"popularidade":1.859}
{"nome":"Brian Yuzna","genero":2,"popularidade":7.215}
{"nome":"Victor Garc\u00eda","genero":0,"popularidade":0.6}
{"nome":"Robin Campillo","genero":2,"popularidade":3.326}
{"nome":"Eitan Arrusi","genero":0,"popularidade":3.977}
{"nome":"Juno Mak","genero":2,"popularidade":6.177}
{"nome":"Gore Verbinski","genero":2,"popularidade":4.274}
{"nome":"Hideo Nakata","genero":2,"popularidade":6.038}
{"nome":"F. Javier Guti\u00e9rrez","genero":0,"popularidade":1.049}
{"nome":"Alan Gibson","genero":2,"popularidade":2.175}
{"nome":"Brian O'Hara","genero":0,"popularidade":0.6}
{"nome":"Jim Sharman","genero":2,"popularidade":3.349}
{"nome":"Rodney Ascher","genero":2,"popularidade":6.09}
{"nome":"Michael Hurst","genero":2,"popularidade":10.653}
{"nome":"Mike Hurst","genero":0,"popularidade":0.84}
{"nome":"Tommy Stovall","genero":0,"popularidade":0.729}
{"nome":"Jordan Galland","genero":2,"popularidade":3.227}
{"nome":"Quentin Dupieux","genero":2,"popularidade":1.99}
{"nome":"Preston DeFrancis","genero":0,"popularidade":0.6}
{"nome":"Simon Barrett","genero":2,"popularidade":3.589}
{"nome":"Adam Wingard","genero":2,"popularidade":9.3}
{"nome":"Gareth Evans","genero":2,"popularidade":5.63}
{"nome":"Jason Eisener","genero":2,"popularidade":1.501}
{"nome":"James D.R. Hickox","genero":2,"popularidade":2.236}
{"nome":"James Landis","genero":2,"popularidade":3.102}
{"nome":"Lawrence Gough","genero":2,"popularidade":2.743}
{"nome":"Kim Ki-duk","genero":2,"popularidade":7.659}
{"nome":"Alejandro Jodorowsky","genero":2,"popularidade":5.674}
{"nome":"James Felix McKenney","genero":2,"popularidade":0.618}
{"nome":"Chelsea Stardust","genero":1,"popularidade":1.388}
{"nome":"Dante Tomaselli","genero":0,"popularidade":2.744}
{"nome":"Howard R. Cohen","genero":2,"popularidade":2.063}
{"nome":"David Hackl","genero":2,"popularidade":2.163}
{"nome":"William Wesley","genero":2,"popularidade":1.517}
{"nome":"Roy Ward Baker","genero":2,"popularidade":3.244}
{"nome":"Keenen Ivory Wayans","genero":2,"popularidade":12.595}
{"nome":"Malcolm D. Lee","genero":2,"popularidade":5.671}
{"nome":"Andr\u00e9 \u00d8vredal","genero":2,"popularidade":3.24}
{"nome":"Chuck Russell","genero":2,"popularidade":8.204}
{"nome":"Neasa Hardiman","genero":1,"popularidade":2.136}
{"nome":"John Frankenheimer","genero":2,"popularidade":5.002}
{"nome":"Don Mancini","genero":2,"popularidade":10.072}
{"nome":"Owen Long","genero":0,"popularidade":1.96}
{"nome":"Yeon Sang-ho","genero":2,"popularidade":4.803}
{"nome":"Brad Anderson","genero":2,"popularidade":5.545}
{"nome":"Carl Schultz","genero":2,"popularidade":2.192}
{"nome":"Frank Henenlotter","genero":2,"popularidade":5.228}
{"nome":"Federico Zampaglione","genero":2,"popularidade":1.955}
{"nome":"E. Elias Merhige","genero":2,"popularidade":3.52}
{"nome":"Sheldon Wilson","genero":2,"popularidade":3.811}
{"nome":"David Worth","genero":0,"popularidade":1.034}
{"nome":"David R. Ellis","genero":2,"popularidade":4.194}
{"nome":"Anthony C. Ferrante","genero":2,"popularidade":3.653}
{"nome":"Kim Chapiron","genero":0,"popularidade":1.165}
{"nome":"Roy William Neill","genero":2,"popularidade":2.988}
{"nome":"Michael Reich","genero":0,"popularidade":0.6}
{"nome":"Jean Yarbrough","genero":2,"popularidade":2.051}
{"nome":"Stanley Kubrick","genero":2,"popularidade":11.658}
{"nome":"John Blanchard","genero":2,"popularidade":1.287}
{"nome":"Paddy Breathnach","genero":2,"popularidade":8.285}
{"nome":"Banjong Pisanthanakun","genero":2,"popularidade":3.172}
{"nome":"Parkpoom Wongpoom","genero":2,"popularidade":2.088}
{"nome":"David Bruckner","genero":2,"popularidade":6.006}
{"nome":"Jacob Gentry","genero":2,"popularidade":1.4}
{"nome":"Dan Bush","genero":2,"popularidade":2.514}
{"nome":"Jonathan Demme","genero":2,"popularidade":6.69}
{"nome":"Christophe Gans","genero":2,"popularidade":8.479}
{"nome":"Steven C. Miller","genero":2,"popularidade":1.819}
{"nome":"Michael Miller","genero":2,"popularidade":5.119}
{"nome":"Scott Derrickson","genero":2,"popularidade":5.358}
{"nome":"Dick Maas","genero":2,"popularidade":4.049}
{"nome":"Gregg Bishop","genero":2,"popularidade":1.4}
{"nome":"Jim Isaac","genero":0,"popularidade":0.6}
{"nome":"Rob Cohen","genero":2,"popularidade":9.258}
{"nome":"George Dugdale","genero":2,"popularidade":1.932}
{"nome":"Mark Ezra","genero":2,"popularidade":1.254}
{"nome":"Crispian Mills","genero":2,"popularidade":3.063}
{"nome":"Robert Hiltzik","genero":2,"popularidade":3.985}
{"nome":"Michael A. Simpson","genero":2,"popularidade":1.631}
{"nome":"Tim Burton","genero":2,"popularidade":13.276}
{"nome":"Austin Vesely","genero":2,"popularidade":0.6}
{"nome":"Jonathan Hopkins","genero":0,"popularidade":1.382}
{"nome":"Amy Holden Jones","genero":1,"popularidade":1.683}
{"nome":"Michael Gallagher","genero":0,"popularidade":0.764}
{"nome":"Michael J. Gallagher","genero":2,"popularidade":1.736}
{"nome":"Stephen Cedars","genero":0,"popularidade":0.6}
{"nome":"Benji Kleiman","genero":0,"popularidade":0.98}
{"nome":"Michael Cohn","genero":2,"popularidade":4.252}
{"nome":"Stephen Portland","genero":0,"popularidade":0.857}
{"nome":"Tom McLoughlin","genero":2,"popularidade":2.954}
{"nome":"William Berke","genero":2,"popularidade":2.712}
{"nome":"Daniel Berk","genero":0,"popularidade":0.6}
{"nome":"Jun Fukuda","genero":2,"popularidade":2.467}
{"nome":"Rowland V. Lee","genero":2,"popularidade":1.883}
{"nome":"Michael Reeves","genero":2,"popularidade":2.38}
{"nome":"Stewart Hendler","genero":2,"popularidade":3.79}
{"nome":"Stephen Carpenter","genero":2,"popularidade":4.02}
{"nome":"Ben Kingsley","genero":2,"popularidade":26.323}
{"nome":"Patrick Horvath","genero":2,"popularidade":0.689}
{"nome":"Roxanne Benjamin","genero":1,"popularidade":5.557}
{"nome":"Mark A.Z. Dipp\u00e9","genero":2,"popularidade":2.807}
{"nome":"Jack Hill","genero":2,"popularidade":2.979}
{"nome":"David Smith","genero":2,"popularidade":0.6}
{"nome":"Simeon Halligan","genero":0,"popularidade":1.344}
{"nome":"M. Night Shyamalan","genero":2,"popularidade":12.166}
{"nome":"Eugene Kotlyarenko","genero":2,"popularidade":6.818}
{"nome":"Egor Abramenko","genero":2,"popularidade":1.488}
{"nome":"Jerome Sable","genero":2,"popularidade":1.859}
{"nome":"Bo Zenga","genero":2,"popularidade":5.11}
{"nome":"A.T. White","genero":2,"popularidade":0.6}
{"nome":"Edward Neumeier","genero":2,"popularidade":2.11}
{"nome":"Norman Jewison","genero":2,"popularidade":5.715}
{"nome":"Joseph Ruben","genero":2,"popularidade":2.9}
{"nome":"Ralph S. Singleton","genero":2,"popularidade":1.587}
{"nome":"Daniel Attias","genero":2,"popularidade":1.929}
{"nome":"Tom Holland","genero":2,"popularidade":47.272}
{"nome":"Rupert Wainwright","genero":2,"popularidade":3.041}
{"nome":"Tommy Chong","genero":2,"popularidade":9.062}
{"nome":"Brandon Christensen","genero":0,"popularidade":2.667}
{"nome":"David Koepp","genero":2,"popularidade":10.726}
{"nome":"Adiya Imri Orr","genero":0,"popularidade":0.6}
{"nome":"Park Chan-wook","genero":2,"popularidade":8.76}
{"nome":"Johannes Roberts","genero":2,"popularidade":7.387}
{"nome":"Edgar G. Ulmer","genero":2,"popularidade":1.385}
{"nome":"John Pieplow","genero":2,"popularidade":3.181}
{"nome":"Colin Bemis","genero":0,"popularidade":1.4}
{"nome":"Mickey Rose","genero":2,"popularidade":7.116}
{"nome":"Philip Chidel","genero":2,"popularidade":1.788}
{"nome":"Tony Krantz","genero":2,"popularidade":3.172}
{"nome":"Ted Nicolaou","genero":2,"popularidade":7.731}
{"nome":"Joseph L. Mankiewicz","genero":2,"popularidade":4.384}
{"nome":"Alberto Marini","genero":2,"popularidade":5.169}
{"nome":"Onur Tukel","genero":2,"popularidade":3.176}
{"nome":"Ben Cresciman","genero":0,"popularidade":2.416}
{"nome":"Peter George","genero":2,"popularidade":0.6}
{"nome":"Luca Guadagnino","genero":2,"popularidade":6.419}
{"nome":"Irwin Allen","genero":2,"popularidade":5.283}
{"nome":"J.D. Dillard","genero":2,"popularidade":1.812}
{"nome":"John Polson","genero":2,"popularidade":7.127}
{"nome":"Matteo Garrone","genero":2,"popularidade":4.767}
{"nome":"Gilbert Adler","genero":2,"popularidade":5.726}
{"nome":"John Harrison","genero":2,"popularidade":6.164}
{"nome":"Rusty Cundieff","genero":2,"popularidade":4.504}
{"nome":"Darin Scott","genero":2,"popularidade":1.4}
{"nome":"Jeremy Haft","genero":2,"popularidade":2.373}
{"nome":"Matthew Bright","genero":2,"popularidade":6.121}
{"nome":"Mitchell Lichtenstein","genero":2,"popularidade":3.36}
{"nome":"Ulli Lommel","genero":2,"popularidade":6.416}
{"nome":"Damien Leone","genero":2,"popularidade":13.357}
{"nome":"Lance W. Dreesen","genero":2,"popularidade":0.6}
{"nome":"Clint Hutchison","genero":2,"popularidade":2.323}
{"nome":"Roger Spottiswoode","genero":2,"popularidade":5.494}
{"nome":"Harold Greenberg","genero":0,"popularidade":1.4}
{"nome":"Anne Henderson","genero":1,"popularidade":0.6}
{"nome":"John Luessenhop","genero":2,"popularidade":2.839}
{"nome":"Marcus Nispel","genero":2,"popularidade":6.087}
{"nome":"Kim Henkel","genero":2,"popularidade":6.223}
{"nome":"Ted Post","genero":2,"popularidade":5.066}
{"nome":"Rob Green","genero":2,"popularidade":2.39}
{"nome":"Sam Raimi","genero":2,"popularidade":11.9}
{"nome":"Bert I. Gordon","genero":2,"popularidade":3.9}
{"nome":"Chris Sivertson","genero":2,"popularidade":4.388}
{"nome":"Eytan Rockaway","genero":0,"popularidade":2.258}
{"nome":"Angela Bettis","genero":1,"popularidade":8.137}
{"nome":"Bruno Forzani","genero":2,"popularidade":1.898}
{"nome":"Kaare Andrews","genero":2,"popularidade":0.914}
{"nome":"Ernesto D\u00edaz Espinoza","genero":2,"popularidade":3.074}
{"nome":"Xavier Gens","genero":2,"popularidade":2.763}
{"nome":"Jorge Michel Grau","genero":2,"popularidade":0.97}
{"nome":"Anders Morgenthaler","genero":2,"popularidade":1.38}
{"nome":"Yoshihiro Nishimura","genero":2,"popularidade":6.934}
{"nome":"H\u00e9l\u00e8ne Cattet","genero":1,"popularidade":3.948}
{"nome":"Marcel Sarmiento","genero":2,"popularidade":2.174}
{"nome":"Tak Sakaguchi","genero":2,"popularidade":9.002}
{"nome":"Jon Schnepp","genero":2,"popularidade":1.793}
{"nome":"Andrew Traucki","genero":2,"popularidade":5.128}
{"nome":"Nacho Vigalondo","genero":2,"popularidade":2.653}
{"nome":"Jake West","genero":2,"popularidade":2.552}
{"nome":"Ti West","genero":2,"popularidade":4.419}
{"nome":"Yudai Yamaguchi","genero":2,"popularidade":7.73}
{"nome":"Lee Hardcastle","genero":2,"popularidade":4.519}
{"nome":"Stuart Rosenberg","genero":2,"popularidade":2.054}
{"nome":"Todd Lincoln","genero":0,"popularidade":1.181}
{"nome":"Nick Murphy","genero":2,"popularidade":5.096}
{"nome":"Jennifer Kent","genero":1,"popularidade":3.424}
{"nome":"McG","genero":2,"popularidade":1.83}
{"nome":"Koldo Serra","genero":2,"popularidade":2.251}
{"nome":"Danishka Esterhazy","genero":1,"popularidade":2.548}
{"nome":"Blair Erickson","genero":0,"popularidade":2.744}
{"nome":"Nathan Ives","genero":2,"popularidade":1.907}
{"nome":"Brian M. Conley","genero":0,"popularidade":1.38}
{"nome":"Jeremy Gardner","genero":2,"popularidade":9.229}
{"nome":"Barry Levinson","genero":2,"popularidade":6.429}
{"nome":"James Kelley","genero":0,"popularidade":0.6}
{"nome":"Robert Florey","genero":2,"popularidade":4.741}
{"nome":"John Schlesinger","genero":2,"popularidade":3.152}
{"nome":"Greg McLean","genero":2,"popularidade":4.23}
{"nome":"Brian Hanson","genero":0,"popularidade":1.38}
{"nome":"Philip Gelatt","genero":2,"popularidade":2.33}
{"nome":"Irvin S. Yeaworth Jr.","genero":2,"popularidade":1.283}
{"nome":"William Brent Bell","genero":2,"popularidade":3.627}
{"nome":"Stacy Title","genero":1,"popularidade":3.088}
{"nome":"Drew Goddard","genero":2,"popularidade":4.372}
{"nome":"Robert Wiene","genero":2,"popularidade":4.666}
{"nome":"Ivan Kavanagh","genero":2,"popularidade":2.383}
{"nome":"Guto Parente","genero":2,"popularidade":0.6}
{"nome":"Elliot Silverstein","genero":2,"popularidade":4.297}
{"nome":"Tarsem Singh","genero":2,"popularidade":7.105}
{"nome":"Michael Melski","genero":2,"popularidade":1.632}
{"nome":"Michele Soavi","genero":2,"popularidade":7.505}
{"nome":"Bobby Miller","genero":2,"popularidade":3.753}
{"nome":"Duncan Skiles","genero":2,"popularidade":2.072}
{"nome":"Marcus Dunstan","genero":2,"popularidade":9.719}
{"nome":"Christopher MacBride","genero":2,"popularidade":3.637}
{"nome":"Matthew Currie Holmes","genero":2,"popularidade":5.792}
{"nome":"Michael Chaves","genero":2,"popularidade":17.899}
{"nome":"Giles Alderson","genero":2,"popularidade":1.384}
{"nome":"Justin P. Lange","genero":2,"popularidade":1.4}
{"nome":"Nikolaj Arcel","genero":2,"popularidade":3.521}
{"nome":"Chris Gorak","genero":2,"popularidade":1.4}
{"nome":"Howard J. Ford","genero":2,"popularidade":1.232}
{"nome":"Jim Jarmusch","genero":2,"popularidade":8.14}
{"nome":"Gabriel Carrer","genero":0,"popularidade":0.84}
{"nome":"Zachary Donohue","genero":0,"popularidade":1.4}
{"nome":"Jon Harris","genero":2,"popularidade":6.592}
{"nome":"Sean Byrne","genero":2,"popularidade":0.6}
{"nome":"Aislinn Clarke","genero":0,"popularidade":0.6}
{"nome":"Paul Campion","genero":0,"popularidade":1.4}
{"nome":"Alistair Legrand","genero":0,"popularidade":3.236}
{"nome":"Miles Doleac","genero":2,"popularidade":8.766}
{"nome":"Abel Ferrara","genero":2,"popularidade":12.225}
{"nome":"Sean Weathers","genero":2,"popularidade":0.6}
{"nome":"Renny Harlin","genero":2,"popularidade":7.108}
{"nome":"Adam Brooks","genero":2,"popularidade":3.207}
{"nome":"Matthew Kennedy","genero":2,"popularidade":2.562}
{"nome":"Nicolas Pesce","genero":2,"popularidade":3.579}
{"nome":"Severin Fiala","genero":2,"popularidade":2.615}
{"nome":"Katrin Gebbe","genero":1,"popularidade":2.271}
{"nome":"Yannis Veslemes","genero":2,"popularidade":0.983}
{"nome":"Veronika Franz","genero":1,"popularidade":1.395}
{"nome":"Ashim Ahluwalia","genero":2,"popularidade":2.102}
{"nome":"Can Evrenol","genero":2,"popularidade":3.654}
{"nome":"Todd Strauss-Schulson","genero":2,"popularidade":1.708}
{"nome":"Timothy Woodward Jr.","genero":2,"popularidade":2.128}
{"nome":"Gerard McMurray","genero":0,"popularidade":1.96}
{"nome":"Jason Zada","genero":2,"popularidade":2.829}
{"nome":"Jos\u00e9 Pedro Lopes","genero":2,"popularidade":0.6}
{"nome":"Peter Jackson","genero":2,"popularidade":18.009}
{"nome":"Tony D'Aquino","genero":2,"popularidade":1.094}
{"nome":"Travis Cluff","genero":2,"popularidade":1.878}
{"nome":"John Carlos Frey","genero":0,"popularidade":0.6}
{"nome":"Douglas Hickox","genero":2,"popularidade":1.519}
{"nome":"Eug\u00e8ne Louri\u00e9","genero":2,"popularidade":3.344}
{"nome":"David Riker","genero":2,"popularidade":1.4}
{"nome":"Doron Paz","genero":2,"popularidade":2.326}
{"nome":"Yoav Paz","genero":2,"popularidade":1.926}
{"nome":"Corin Hardy","genero":2,"popularidade":11.143}
{"nome":"D.W. Young","genero":0,"popularidade":0.84}
{"nome":"Tom Elkins","genero":2,"popularidade":2.993}
{"nome":"Daniel Farrands","genero":2,"popularidade":5.137}
{"nome":"Jordan Downey","genero":2,"popularidade":1.4}
{"nome":"Lee Cronin","genero":2,"popularidade":6.297}
{"nome":"Benjamin Rocher","genero":2,"popularidade":2.691}
{"nome":"Yannick Dahan","genero":2,"popularidade":1.988}
{"nome":"Jimmy Sangster","genero":2,"popularidade":1.678}
{"nome":"Grady Granros","genero":0,"popularidade":0.6}
{"nome":"Justin Powers","genero":0,"popularidade":2.26}
{"nome":"Elias","genero":0,"popularidade":0.6}
{"nome":"Jane Rose","genero":1,"popularidade":5.967}
{"nome":"Ashley Thorpe","genero":2,"popularidade":2.588}
{"nome":"Tomas Almgren","genero":0,"popularidade":0.6}
{"nome":"Simon Ruben","genero":0,"popularidade":0.6}
{"nome":"Brian Barnes","genero":0,"popularidade":0.84}
{"nome":"Doug Sakmann","genero":0,"popularidade":0.6}
{"nome":"David Blyth","genero":0,"popularidade":2.749}
{"nome":"Jim Isaac","genero":0,"popularidade":0.6}
{"nome":"James Isaac","genero":2,"popularidade":4.056}
{"nome":"Andy Newbery","genero":2,"popularidade":1.158}
{"nome":"Ti West","genero":2,"popularidade":4.419}
{"nome":"Lars von Trier","genero":2,"popularidade":15.138}
{"nome":"Derek Nguyen","genero":2,"popularidade":1.548}
{"nome":"Bobby Roe","genero":2,"popularidade":1.502}
{"nome":"Tom Six","genero":2,"popularidade":4.484}
{"nome":"Paul Hough","genero":2,"popularidade":0.6}
{"nome":"Tony Scott","genero":2,"popularidade":13.306}
{"nome":"Thomas Szczepanski","genero":2,"popularidade":0.6}
{"nome":"Craig Zobel","genero":2,"popularidade":3.524}
{"nome":"Megan Freels Johnston","genero":0,"popularidade":0.6}
{"nome":"Denis Rovira","genero":0,"popularidade":0.6}
{"nome":"James Franco","genero":2,"popularidade":17.085}
{"nome":"Leigh Whannell","genero":2,"popularidade":6.889}
{"nome":"Matthew Butler-Hart","genero":2,"popularidade":0.694}
{"nome":"Lawrence Fowler","genero":2,"popularidade":1.62}
{"nome":"Mischa Webley","genero":0,"popularidade":0.6}
{"nome":"Kristian Levring","genero":2,"popularidade":1.4}
{"nome":"David Pastor","genero":2,"popularidade":5.505}
{"nome":"Alex Pastor","genero":0,"popularidade":0.6}
{"nome":"Ed Gass-Donnelly","genero":2,"popularidade":1.856}
{"nome":"Anthony C. Ferrante","genero":2,"popularidade":3.653}
{"nome":"Tom Hammock","genero":2,"popularidade":2.705}
{"nome":"David Gelb","genero":2,"popularidade":2.313}
{"nome":"Robert Eggers","genero":2,"popularidade":8.938}
{"nome":"Juan Carlos Medina","genero":2,"popularidade":2.542}
{"nome":"Lenny Abrahamson","genero":2,"popularidade":5.067}
{"nome":"Brian O'Malley","genero":0,"popularidade":0.6}
{"nome":"Rob Zombie","genero":2,"popularidade":7.51}
{"nome":"Anna Biller","genero":1,"popularidade":2.25}
{"nome":"Sean Byrne","genero":2,"popularidade":0.6}
{"nome":"Edgar G. Ulmer","genero":2,"popularidade":1.385}
{"nome":"Jon Turteltaub","genero":2,"popularidade":6.398}
{"nome":"Danny Pang","genero":2,"popularidade":2.153}
{"nome":"Travis Zariwny","genero":2,"popularidade":8.331}
{"nome":"Joe Begos","genero":2,"popularidade":2.775}
{"nome":"Bryan Bertino","genero":2,"popularidade":5.068}
{"nome":"Victor Mathieu","genero":0,"popularidade":0.6}
{"nome":"Mary Harron","genero":1,"popularidade":4.005}
{"nome":"Alex Kurtzman","genero":2,"popularidade":6.429}
{"nome":"Jaume Balaguer\u00f3","genero":2,"popularidade":4.028}
{"nome":"Marcus Dunstan","genero":2,"popularidade":9.719}
{"nome":"Nicolas Winding Refn","genero":2,"popularidade":7.701}
{"nome":"Dominique Rocher","genero":0,"popularidade":1.4}
{"nome":"Roberto San Sebasti\u00e1n","genero":0,"popularidade":0.6}
{"nome":"John Rocco","genero":0,"popularidade":1.38}
{"nome":"Abiel Bruhn","genero":0,"popularidade":0.6}
{"nome":"Mitchell Altieri","genero":2,"popularidade":2.092}
{"nome":"Rodney Ascher","genero":2,"popularidade":6.09}
{"nome":"Corin Hardy","genero":2,"popularidade":11.143}
{"nome":"Matt Angel","genero":2,"popularidade":2.355}
{"nome":"Suzanne Coote","genero":1,"popularidade":3.061}
{"nome":"Johannes Roberts","genero":2,"popularidade":7.387}
{"nome":"Nicholas McCarthy","genero":2,"popularidade":1.774}
{"nome":"Dallas Richard Hallam","genero":2,"popularidade":1.396}
{"nome":"Patrick Horvath","genero":2,"popularidade":0.689}
{"nome":"Aaron B. Koontz","genero":2,"popularidade":0.98}
{"nome":"Victor Sj\u00f6str\u00f6m","genero":2,"popularidade":8.186}
{"nome":"Galder Gaztelu-Urrutia","genero":2,"popularidade":3.882}
{"nome":"Ole Bornedal","genero":2,"popularidade":6.464}
{"nome":"Scott B. Hansen","genero":2,"popularidade":0.6}
{"nome":"Diederik Van Rooijen","genero":0,"popularidade":2.005}
{"nome":"Shane Black","genero":2,"popularidade":11.04}
{"nome":"Greg Spence","genero":2,"popularidade":3.982}
{"nome":"James DeMonaco","genero":2,"popularidade":7.81}
{"nome":"Kim Jee-woon","genero":2,"popularidade":6.769}
{"nome":"John Pogue","genero":2,"popularidade":3.744}
{"nome":"Philip Ridley","genero":2,"popularidade":2.694}
{"nome":"Dave Franco","genero":2,"popularidade":17.563}
{"nome":"Lew Landers","genero":2,"popularidade":4.299}
{"nome":"Manuel Carballo","genero":2,"popularidade":0.692}
{"nome":"D. Kerry Prior","genero":2,"popularidade":0.6}
{"nome":"David Bruckner","genero":2,"popularidade":6.006}
{"nome":"Yam Laranas","genero":2,"popularidade":3.172}
{"nome":"Kenny Ortega","genero":2,"popularidade":4.857}
{"nome":"Christian E. Christiansen","genero":2,"popularidade":0.66}
{"nome":"Carter Smith","genero":2,"popularidade":3.426}
{"nome":"Paul Hyett","genero":0,"popularidade":4.961}
{"nome":"Michael Winner","genero":2,"popularidade":7.826}
{"nome":"Frank Sabatella","genero":0,"popularidade":2.887}
{"nome":"John R. Leonetti","genero":2,"popularidade":3.569}
{"nome":"Caryn Waechter","genero":1,"popularidade":1.166}
{"nome":"Harold H\u00f6lscher","genero":2,"popularidade":1.38}
{"nome":"Adam Robitel","genero":2,"popularidade":7.493}
{"nome":"Pascal Laugier","genero":2,"popularidade":7.733}
{"nome":"Jonathan Liebesman","genero":2,"popularidade":1.989}
{"nome":"Jeremy Kasten","genero":2,"popularidade":1.589}
{"nome":"Tom Savini","genero":2,"popularidade":30.122}
{"nome":"Richard Stanley","genero":2,"popularidade":6.789}
{"nome":"Buddy Giovinazzo","genero":2,"popularidade":1.949}
{"nome":"Karim Hussain","genero":2,"popularidade":3.386}
{"nome":"Douglas Buck","genero":2,"popularidade":2.869}
{"nome":"Matthijs van Heijningen Jr.","genero":2,"popularidade":3.119}
{"nome":"Lee Frost","genero":2,"popularidade":1.904}
{"nome":"Robert H. Lieberman","genero":2,"popularidade":2.154}
{"nome":"Alfonso Gomez-Rejon","genero":2,"popularidade":2.246}
{"nome":"Michael Herz","genero":2,"popularidade":3.135}
{"nome":"Lloyd Kaufman","genero":2,"popularidade":6.872}
{"nome":"Michael Oblowitz","genero":2,"popularidade":2.596}
{"nome":"Carlo Ledesma","genero":2,"popularidade":1.693}
{"nome":"Geoff Redknap","genero":0,"popularidade":1.728}
{"nome":"Jim O'Connolly","genero":2,"popularidade":1.932}
{"nome":"Mark Neveldine","genero":2,"popularidade":2.74}
{"nome":"Dan Bush","genero":2,"popularidade":2.514}
{"nome":"M. Night Shyamalan","genero":2,"popularidade":12.166}
{"nome":"Giulio Paradisi","genero":2,"popularidade":2.003}
{"nome":"Jeremy Gillespie","genero":2,"popularidade":2.828}
{"nome":"Steven Kostanski","genero":2,"popularidade":9.475}
{"nome":"Byron Haskin","genero":2,"popularidade":6.213}
{"nome":"John Carpenter","genero":2,"popularidade":13.512}
{"nome":"Robin Hardy","genero":2,"popularidade":4.601}
{"nome":"Neil LaBute","genero":2,"popularidade":2.177}
{"nome":"Emma Tammi","genero":1,"popularidade":14.16}
{"nome":"Nick Jongerius","genero":0,"popularidade":1.96}
{"nome":"Nicolas Roeg","genero":2,"popularidade":3.041}
{"nome":"Lucky McKee","genero":2,"popularidade":3.063}
{"nome":"James Watkins","genero":2,"popularidade":8.703}
{"nome":"Tom Harper","genero":2,"popularidade":5.157}
{"nome":"Brett Pierce","genero":0,"popularidade":0.98}
{"nome":"Drew T. Pierce","genero":2,"popularidade":0.6}
{"nome":"Douglas Hickox","genero":2,"popularidade":1.519}
{"nome":"David Moreau","genero":2,"popularidade":3.868}
{"nome":"Xavier Palud","genero":2,"popularidade":2.04}
{"nome":"Ernie Barbarash","genero":2,"popularidade":5.263}
{"nome":"John-Paul Panelli","genero":0,"popularidade":0.6}
{"nome":"Jay Lender","genero":2,"popularidade":1.4}
{"nome":"Micah Wright","genero":0,"popularidade":1.049}
{"nome":"Tom Holland","genero":2,"popularidade":47.272}
{"nome":"Steve Beck","genero":2,"popularidade":3.732}
{"nome":"Seth Rogen","genero":2,"popularidade":18.589}
{"nome":"Evan Goldberg","genero":2,"popularidade":5.69}
{"nome":"Takashi Miike","genero":2,"popularidade":11.539}
{"nome":"Fruit Chan","genero":2,"popularidade":4.574}
{"nome":"Park Chan-wook","genero":2,"popularidade":8.76}
{"nome":"Nonzee Nimibutr","genero":2,"popularidade":2.563}
{"nome":"Dallas Jackson","genero":0,"popularidade":1.646}
{"nome":"Tony Giglio","genero":2,"popularidade":2.835}
{"nome":"William Castle","genero":2,"popularidade":3.353}
{"nome":"Peter Sykes","genero":2,"popularidade":2.565}
{"nome":"Jason Axinn","genero":0,"popularidade":2.651}
{"nome":"Jason Banker","genero":2,"popularidade":0.668}
{"nome":"Yoshihiro Nishimura","genero":2,"popularidade":6.934}
{"nome":"Amando de Ossorio","genero":2,"popularidade":2.975}
{"nome":"Tobe Hooper","genero":2,"popularidade":4.255}
{"nome":"Mark Young","genero":2,"popularidade":2.842}
{"nome":"Charles B. Pierce","genero":2,"popularidade":2.069}
{"nome":"Yeon Sang-ho","genero":2,"popularidade":4.803}
{"nome":"Rudy De Luca","genero":2,"popularidade":4.585}
{"nome":"Harmony Korine","genero":2,"popularidade":10.098}
{"nome":"Marc Evans","genero":2,"popularidade":3.801}
{"nome":"S.S. Wilson","genero":2,"popularidade":4.347}
{"nome":"Brent Maddock","genero":2,"popularidade":2.691}
{"nome":"Don Michael Paul","genero":2,"popularidade":12.221}
{"nome":"Patrick Lussier","genero":2,"popularidade":4.663}
{"nome":"Michael Dougherty","genero":2,"popularidade":3.471}
{"nome":"Freddie Francis","genero":2,"popularidade":5.284}
{"nome":"Claire Denis","genero":1,"popularidade":5.451}
{"nome":"Robert Heath","genero":2,"popularidade":1.15}
{"nome":"Eli Craig","genero":2,"popularidade":6.763}
{"nome":"John Stockwell","genero":2,"popularidade":12.87}
{"nome":"Joe May","genero":2,"popularidade":2.23}
{"nome":"Sidney Salkow","genero":2,"popularidade":1.381}
{"nome":"Catherine Hardwicke","genero":1,"popularidade":5.557}
{"nome":"Chris Weitz","genero":2,"popularidade":8.558}
{"nome":"Joe Dante","genero":2,"popularidade":4.081}
{"nome":"John Landis","genero":2,"popularidade":8.039}
{"nome":"Steven Spielberg","genero":2,"popularidade":24.334}
{"nome":"Francis Ford Coppola","genero":2,"popularidade":10.599}
{"nome":"George A. Romero","genero":2,"popularidade":5.741}
{"nome":"Dario Argento","genero":2,"popularidade":9.252}
{"nome":"William Conrad","genero":2,"popularidade":7.529}
{"nome":"Herschell Gordon Lewis","genero":2,"popularidade":3.693}
{"nome":"Tyler Perry","genero":2,"popularidade":13.397}
{"nome":"Matthew J. Lawrence","genero":0,"popularidade":0.6}
{"nome":"William Lustig","genero":2,"popularidade":3.812}
{"nome":"Michael Spierig","genero":2,"popularidade":4.543}
{"nome":"Peter Spierig","genero":2,"popularidade":4.358}
{"nome":"Babak Anvari","genero":2,"popularidade":1.732}
{"nome":"Len Wiseman","genero":2,"popularidade":9.468}
{"nome":"Bj\u00f6rn Stein","genero":2,"popularidade":6.788}
{"nome":"M\u00e5ns M\u00e5rlind","genero":2,"popularidade":7.98}
{"nome":"Anna Foerster","genero":1,"popularidade":3.202}
{"nome":"Patrick Tatopoulos","genero":2,"popularidade":5.565}
{"nome":"Stephen Susco","genero":2,"popularidade":2.613}
{"nome":"Thomas Guard","genero":2,"popularidade":0.828}
{"nome":"Charles Guard","genero":2,"popularidade":3.316}
{"nome":"Jaume Collet-Serra","genero":2,"popularidade":6.14}
{"nome":"Jamie Blanks","genero":2,"popularidade":2.949}
{"nome":"Mary Lambert","genero":1,"popularidade":7.093}
{"nome":"John Ottman","genero":2,"popularidade":4.614}
{"nome":"Jordan Peele","genero":2,"popularidade":9.34}
{"nome":"Joseph Martin","genero":0,"popularidade":0.6}
{"nome":"Nimr\u00f3d Antal","genero":2,"popularidade":8.501}
{"nome":"Richard Wenk","genero":2,"popularidade":7.573}
{"nome":"Frank R. Strayer","genero":0,"popularidade":2.09}
{"nome":"Wes Craven","genero":2,"popularidade":6.705}
{"nome":"Paul Weitz","genero":2,"popularidade":4.11}
{"nome":"Robert Bierman","genero":2,"popularidade":2.852}
{"nome":"Tommy Lee Wallace","genero":2,"popularidade":4.966}
{"nome":"John Bacchus","genero":2,"popularidade":2.061}
{"nome":"Carl Theodor Dreyer","genero":2,"popularidade":2.735}
{"nome":"Jes\u00fas Franco","genero":2,"popularidade":16.666}
{"nome":"Stephen Sommers","genero":2,"popularidade":13.2}
{"nome":"Brad Anderson","genero":2,"popularidade":5.545}
{"nome":"Glenn Danzig","genero":2,"popularidade":4.158}
{"nome":"Abel Ferry","genero":2,"popularidade":1.832}
{"nome":"Adam Wingard","genero":2,"popularidade":9.3}
{"nome":"Glenn McQuaid","genero":2,"popularidade":2.313}
{"nome":"Joe Swanberg","genero":2,"popularidade":3.448}
{"nome":"Gregg Bishop","genero":2,"popularidade":1.4}
{"nome":"Justin Benson","genero":2,"popularidade":9.849}
{"nome":"Aaron Moorhead","genero":2,"popularidade":3.201}
{"nome":"Marcel Sarmiento","genero":2,"popularidade":2.174}
{"nome":"Nacho Vigalondo","genero":2,"popularidade":2.653}
{"nome":"Adam Green","genero":2,"popularidade":4.185}
{"nome":"David Cronenberg","genero":2,"popularidade":12.039}
{"nome":"Henry Joost","genero":2,"popularidade":2.613}
{"nome":"Ariel Schulman","genero":2,"popularidade":8.13}
{"nome":"Brett Leonard","genero":2,"popularidade":3.416}
{"nome":"Tom Costabile","genero":0,"popularidade":0.6}
{"nome":"Bryan Johnson","genero":2,"popularidade":3.761}
{"nome":"David Keating","genero":2,"popularidade":4.274}
{"nome":"Steve Miner","genero":2,"popularidade":3.978}
{"nome":"Hal Barwood","genero":2,"popularidade":3.114}
{"nome":"Anthony Hickox","genero":2,"popularidade":4.256}
{"nome":"Ted Geoghegan","genero":2,"popularidade":2.172}
{"nome":"Dennis Gansel","genero":2,"popularidade":7.336}
{"nome":"Jim Mickle","genero":2,"popularidade":2.492}
{"nome":"Marc Meyers","genero":2,"popularidade":1.165}
{"nome":"Larry Fessenden","genero":2,"popularidade":7.805}
{"nome":"Jean Yarbrough","genero":2,"popularidade":2.051}
{"nome":"Stuart Walker","genero":2,"popularidade":3.461}
{"nome":"Louis Morneau","genero":2,"popularidade":2.085}
{"nome":"Adam Grossman","genero":2,"popularidade":1.553}
{"nome":"Robert Aldrich","genero":2,"popularidade":6.687}
{"nome":"Robert Zemeckis","genero":2,"popularidade":10.531}
{"nome":"Simon West","genero":2,"popularidade":3.096}
{"nome":"Fred Walton","genero":2,"popularidade":2.474}
{"nome":"Susan Montford","genero":1,"popularidade":1.4}
{"nome":"Paul Raschid","genero":0,"popularidade":0.681}
{"nome":"Geoffrey Sax","genero":2,"popularidade":3.58}
{"nome":"Victor Halperin","genero":2,"popularidade":5.621}
{"nome":"Richie Moore","genero":0,"popularidade":1.96}
{"nome":"J.S. Cardone","genero":2,"popularidade":0.84}
{"nome":"Fritz B\u00f6hm","genero":2,"popularidade":0.972}
{"nome":"Glen Morgan","genero":2,"popularidade":2.748}
{"nome":"Bobcat Goldthwait","genero":2,"popularidade":11.468}
{"nome":"Gregory Jacobs","genero":2,"popularidade":1.944}
{"nome":"Greg Jacobs","genero":0,"popularidade":0.6}
{"nome":"Robert Kurtzman","genero":2,"popularidade":6.787}
{"nome":"Jack Sholder","genero":2,"popularidade":7.757}
{"nome":"Chris Angel","genero":2,"popularidade":1.64}
{"nome":"Kevin Tenney","genero":2,"popularidade":6.205}
{"nome":"Jordan Barker","genero":2,"popularidade":1.565}
{"nome":"\u00c1lex de la Iglesia","genero":2,"popularidade":1.817}
{"nome":"Greg McLean","genero":2,"popularidade":4.23}
{"nome":"George Waggner","genero":2,"popularidade":5.593}
{"nome":"Lowell Dean","genero":0,"popularidade":1.62}
{"nome":"Michael Wadleigh","genero":2,"popularidade":2.79}
{"nome":"Marc Forster","genero":2,"popularidade":4.757}
{"nome":"Kevin Gates","genero":2,"popularidade":0.84}
{"nome":"Michael Bartlett","genero":0,"popularidade":1.96}
{"nome":"David Guy Levy","genero":2,"popularidade":0.682}
{"nome":"Michael Greenspan","genero":2,"popularidade":1.991}
{"nome":"Rob Schmidt","genero":2,"popularidade":9.6}
{"nome":"Roger Corman","genero":2,"popularidade":9.516}
{"nome":"Roxanne Benjamin","genero":1,"popularidade":5.557}
{"nome":"Annie Clark","genero":1,"popularidade":2.12}
{"nome":"Karyn Kusama","genero":1,"popularidade":4.266}
{"nome":"Andy Mitton","genero":0,"popularidade":3.108}
{"nome":"David Koepp","genero":2,"popularidade":10.726}
{"nome":"Mel Brooks","genero":2,"popularidade":15.304}
{"nome":"Barry Levinson","genero":2,"popularidade":6.429}
{"nome":"Sergio Martino","genero":2,"popularidade":3.716}
{"nome":"Brandon Christensen","genero":0,"popularidade":2.667}
{"nome":"Jordan Rubin","genero":2,"popularidade":2.178}
{"nome":"Lucio Fulci","genero":2,"popularidade":9.064}
{"nome":"Lee Min-jae","genero":2,"popularidade":1.538}
{"nome":"Jay Lee","genero":2,"popularidade":4.4}
{"nome":"Ruben Fleischer","genero":2,"popularidade":6.304}
{"nome":"Kevin Hamedani","genero":2,"popularidade":3.056}
